Workbook
Name Slicer_City: #N/A
Name Slicer_Customer_Name: #N/A
Name Slicer_Months: #N/A
Name Slicer_Product_Sub_Category: #N/A
Name Slicer_Region1: #N/A
Name Slicer_Ship_Mode: #N/A

Sheet Dashboard

Sheet Region vs Salse
A3: Row Labels | B3: Sum of Sales
A4: Central | B4: 448284.7
A5: East | B5: 592171.49
A6: South | B6: 357105.12
A7: West | B7: 526776.57
A8: Grand Total | B8: 1924337.9
A11: =GETPIVOTDATA("Sales",$A$3) -> 1924337.9

Sheet Ship Mode Vs Salse
A3: Row Labels | B3: Sum of Sales
A4: Delivery Truck | B4: 789235.46
A5: Express Air | B5: 145050.22
A6: Regular Air | B6: 990052.2
A7: Grand Total | B7: 1924337.9
A12: =GETPIVOTDATA("Sales",$A$3) -> 1924337.9

Sheet Product
A3: Row Labels | B3: Sum of Sales
A4: Appliances | B4: 82201.15
A5: Binders and Binder Accessories | B5: 185928.14
A6: Bookcases | B6: 107796.09
A7: Chairs & Chairmats | B7: 261072.73
A8: Computer Peripherals | B8: 96261.3
A9: Copiers and Fax | B9: 99069.48
A10: Envelopes | B10: 10479.77
A11: Labels | B11: 4914.82
A12: Office Furnishings | B12: 98070.91
A13: Office Machines | B13: 318169.68
A14: Paper | B14: 55813.92
A15: Pens & Art Supplies | B15: 26071.61
... A21: Grand Total | B21: 1924337.9
B23: =GETPIVOTDATA("Sales",$A$3) -> 1924337.9

Sheet Month
A3: Row Labels | B3: Sum of Sales
A4: January | B4: 274766.92
A5: February | B5: 326101.47
A6: March | B6: 271696.67
A7: April | B7: 389831.95
A8: May | B8: 306572.07
A9: June | B9: 355368.8
A10: Grand Total | B10: 1924337.9

Sheet Customer name 
A3: Row Labels | B3: Sum of Sales
A4: Aaron Day | B4: 710.16
A5: Aaron Dillon | B5: 18.34
A6: Aaron Riggs | B6: 3598.26
A7: Aaron Shaffer | B7: 894.64
A8: Adam G Sawyer | B8: 1638.5
A9: Adam Saunders Gray | B9: 48.3
A10: Albert Frost | B10: 485.01
A11: Albert Maxwell | B11: 396.19
A12: Albert Tyson | B12: 1338.6
A13: Alex Harrell | B13: 267.89
A14: Alex Nicholson | B14: 191.68
A15: Alex Watkins | B15: 205.76
... A1134: Grand Total | B1134: 1924337.9

Sheet Orders
A1: Row ID | B1: Order Priority | C1: Discount | D1: Unit Price | E1: Shipping Cost | F1: Customer ID | G1: Repeat Customers | H1: Customer Name | I1: Ship Mode | J1: Customer Segment | K1: Product Category | L1: Product Sub-Category | M1: Product Container | N1: Product Name | O1: Product Base Margin | P1: Profit Margin | Q1: Country | R1: Region | S1: State or Province | T1: City | U1: Postal Code | V1: Order Date | W1: Order Month | X1: Order Year | Y1: Ship Date | Z1: Profit | AA1: Quantity ordered new | AB1: Sales | AC1: Order ID | AD1: Return Status
A2: 20847 | B2: High | C2: 0.01 | D2: 2.84 | E2: 0.93 | F2: 3 | G2: =IF(COUNTIF(Table1[Customer ID],Table1[[#This Row],[Customer ID]])>1,"Repeat Customer","One-Time Customer") -> One-Time Customer | H2: Bonnie Potter | I2: Express Air | J2: Corporate | K2: Office Supplies | L2: Pens & Art Supplies | M2: Wrap Bag | N2: SANFORD Liquid Accent™ Tank-Style Highlighters | O2: 0.54 | P2: =Table1[[#This Row],[Profit]]/Table1[[#This Row],[Sales]] -> 0.35049962 | Q2: United States | R2: West | S2: Washington | T2: Anacortes | U2: 98221 | V2: 42011 | W2: =TEXT(Table1[[#This Row],[Order Date]],"mmmm") -> January | X2: =TEXT(Table1[[#This Row],[Order Date]],"yyyy") -> 2015 | Y2: 42012 | Z2: 4.56 | AA2: 4 | AB2: 13.01 | AC2: 88522 | AD2: =IF(COUNTIF(Returns!$A$2:$A$1635,Orders!AC2)>0,"Returned","Not Returned") -> Not Returned
A3: 20228 | B3: Not Specified | C3: 0.02 | D3: 500.98 | E3: 26 | F3: 5 | G3: =IF(COUNTIF(Table1[Customer ID],Table1[[#This Row],[Customer ID]])>1,"Repeat Customer","One-Time Customer") -> One-Time Customer | H3: Ronnie Proctor | I3: Delivery Truck | J3: Home Office | K3: Furniture | L3: Chairs & Chairmats | M3: Jumbo Drum | N3: Global Troy™ Executive Leather Low-Back Tilter | O3: 0.6 | P3: =Table1[[#This Row],[Profit]]/Table1[[#This Row],[Sales]] -> 0.69 | Q3: United States | R3: West | S3: California | T3: San Gabriel | U3: 91776 | V3: 42168 | W3: =TEXT(Table1[[#This Row],[Order Date]],"mmmm") -> June | X3: =TEXT(Table1[[#This Row],[Order Date]],"yyyy") -> 2015 | Y3: 42170 | Z3: 4390.3665 | AA3: 12 | AB3: 6362.85 | AC3: 90193 | AD3: =IF(COUNTIF(Returns!$A$2:$A$1635,Orders!AC3)>0,"Returned","Not Returned") -> Not Returned
A4: 21776 | B4: Critical | C4: 0.06 | D4: 9.48 | E4: 7.29 | F4: 11 | G4: =IF(COUNTIF(Table1[Customer ID],Table1[[#This Row],[Customer ID]])>1,"Repeat Customer","One-Time Customer") -> One-Time Customer | H4: Marcus Dunlap | I4: Regular Air | J4: Home Office | K4: Furniture | L4: Office Furnishings | M4: Small Pack | N4: DAX Two-Tone Rosewood/Black Document Frame, Desktop, 5 x 7 | O4: 0.45 | P4: =Table1[[#This Row],[Profit]]/Table1[[#This Row],[Sales]] -> -0.25484063 | Q4: United States | R4: East | S4: New Jersey | T4: Roselle | U4: 7203 | V4: 42050 | W4: =TEXT(Table1[[#This Row],[Order Date]],"mmmm") -> February | X4: =TEXT(Table1[[#This Row],[Order Date]],"yyyy") -> 2015 | Y4: 42052 | Z4: -53.8096 | AA4: 22 | AB4: 211.15 | AC4: 90192 | AD4: =IF(COUNTIF(Returns!$A$2:$A$1635,Orders!AC4)>0,"Returned","Not Returned") -> Not Returned
A5: 24844 | B5: Medium | C5: 0.09 | D5: 78.69 | E5: 19.99 | F5: 14 | G5: =IF(COUNTIF(Table1[Customer ID],Table1[[#This Row],[Customer ID]])>1,"Repeat Customer","One-Time Customer") -> Repeat Customer | H5: Gwendolyn F Tyson | I5: Regular Air | J5: Small Business | K5: Furniture | L5: Office Furnishings | M5: Small Box | N5: Howard Miller 12-3/4 Diameter Accuwave DS ™ Wall Clock | O5: 0.43 | P5: =Table1[[#This Row],[Profit]]/Table1[[#This Row],[Sales]] -> 0.69 | Q5: United States | R5: Central | S5: Minnesota | T5: Prior Lake | U5: 55372 | V5: 42136 | W5: =TEXT(Table1[[#This Row],[Order Date]],"mmmm") -> May | X5: =TEXT(Table1[[#This Row],[Order Date]],"yyyy") -> 2015 | Y5: 42138 | Z5: 803.4705 | AA5: 16 | AB5: 1164.45 | AC5: 86838 | AD5: =IF(COUNTIF(Returns!$A$2:$A$1635,Orders!AC5)>0,"Returned","Not Returned") -> Not Returned
A6: 24846 | B6: Medium | C6: 0.08 | D6: 3.28 | E6: 2.31 | F6: 14 | G6: =IF(COUNTIF(Table1[Customer ID],Table1[[#This Row],[Customer ID]])>1,"Repeat Customer","One-Time Customer") -> Repeat Customer | H6: Gwendolyn F Tyson | I6: Regular Air | J6: Small Business | K6: Office Supplies | L6: Pens & Art Supplies | M6: Wrap Bag | N6: Newell 321 | O6: 0.56 | P6: =Table1[[#This Row],[Profit]]/Table1[[#This Row],[Sales]] -> -1.0809717 | Q6: United States | R6: Central | S6: Minnesota | T6: Prior Lake | U6: 55372 | V6: 42136 | W6: =TEXT(Table1[[#This Row],[Order Date]],"mmmm") -> May | X6: =TEXT(Table1[[#This Row],[Order Date]],"yyyy") -> 2015 | Y6: 42137 | Z6: -24.03 | AA6: 7 | AB6: 22.23 | AC6: 86838 | AD6: =IF(COUNTIF(Returns!$A$2:$A$1635,Orders!AC6)>0,"Returned","Not Returned") -> Not Returned
A7: 24847 | B7: Medium | C7: 0.05 | D7: 3.28 | E7: 4.2 | F7: 14 | G7: =IF(COUNTIF(Table1[Customer ID],Table1[[#This Row],[Customer ID]])>1,"Repeat Customer","One-Time Customer") -> Repeat Customer | H7: Gwendolyn F Tyson | I7: Regular Air | J7: Small Business | K7: Office Supplies | L7: Pens & Art Supplies | M7: Wrap Bag | N7: Newell 351 | O7: 0.56 | P7: =Table1[[#This Row],[Profit]]/Table1[[#This Row],[Sales]] -> -2.6468906 | Q7: United States | R7: Central | S7: Minnesota | T7: Prior Lake | U7: 55372 | V7: 42136 | W7: =TEXT(Table1[[#This Row],[Order Date]],"mmmm") -> May | X7: =TEXT(Table1[[#This Row],[Order Date]],"yyyy") -> 2015 | Y7: 42137 | Z7: -37.03 | AA7: 4 | AB7: 13.99 | AC7: 86838 | AD7: =IF(COUNTIF(Returns!$A$2:$A$1635,Orders!AC7)>0,"Returned","Not Returned") -> Not Returned
A8: 24848 | B8: Medium | C8: 0.05 | D8: 3.58 | E8: 1.63 | F8: 14 | G8: =IF(COUNTIF(Table1[Customer ID],Table1[[#This Row],[Customer ID]])>1,"Repeat Customer","One-Time Customer") -> Repeat Customer | H8: Gwendolyn F Tyson | I8: Regular Air | J8: Small Business | K8: Office Supplies | L8: Rubber Bands | M8: Wrap Bag | N8: OIC Colored Binder Clips, Assorted Sizes | O8: 0.36 | P8: =Table1[[#This Row],[Profit]]/Table1[[#This Row],[Sales]] -> -0.049789621 | Q8: United States | R8: Central | S8: Minnesota | T8: Prior Lake | U8: 55372 | V8: 42136 | W8: =TEXT(Table1[[#This Row],[Order Date]],"mmmm") -> May | X8: =TEXT(Table1[[#This Row],[Order Date]],"yyyy") -> 2015 | Y8: 42137 | Z8: -0.71 | AA8: 4 | AB8: 14.26 | AC8: 86838 | AD8: =IF(COUNTIF(Returns!$A$2:$A$1635,Orders!AC8)>0,"Returned","Not Returned") -> Not Returned
A9: 18181 | B9: Critical | C9: 0 | D9: 4.42 | E9: 4.99 | F9: 15 | G9: =IF(COUNTIF(Table1[Customer ID],Table1[[#This Row],[Customer ID]])>1,"Repeat Customer","One-Time Customer") -> Repeat Customer | H9: Timothy Reese | I9: Regular Air | J9: Small Business | K9: Office Supplies | L9: Envelopes | M9: Small Box | N9: Grip Seal Envelopes | O9: 0.38 | P9: =Table1[[#This Row],[Profit]]/Table1[[#This Row],[Sales]] -> -1.7872722 | Q9: United States | R9: East | S9: New York | T9: Smithtown | U9: 11787 | V9: 42102 | W9: =TEXT(Table1[[#This Row],[Order Date]],"mmmm") -> April | X9: =TEXT(Table1[[#This Row],[Order Date]],"yyyy") -> 2015 | Y9: 42103 | Z9: -59.82 | AA9: 7 | AB9: 33.47 | AC9: 86837 | AD9: =IF(COUNTIF(Returns!$A$2:$A$1635,Orders!AC9)>0,"Returned","Not Returned") -> Not Returned
A10: 20925 | B10: Medium | C10: 0.01 | D10: 35.94 | E10: 6.66 | F10: 15 | G10: =IF(COUNTIF(Table1[Customer ID],Table1[[#This Row],[Customer ID]])>1,"Repeat Customer","One-Time Customer") -> Repeat Customer | H10: Timothy Reese | I10: Regular Air | J10: Small Business | K10: Office Supplies | L10: Envelopes | M10: Small Box | N10: Tyvek ® Top-Opening Peel & Seel ® Envelopes, Gray | O10: 0.4 | P10: =Table1[[#This Row],[Profit]]/Table1[[#This Row],[Sales]] -> 0.69 | Q10: United States | R10: East | S10: New York | T10: Smithtown | U10: 11787 | V10: 42152 | W10: =TEXT(Table1[[#This Row],[Order Date]],"mmmm") -> May | X10: =TEXT(Table1[[#This Row],[Order Date]],"yyyy") -> 2015 | Y10: 42152 | Z10: 261.8757 | AA10: 10 | AB10: 379.53 | AC10: 86839 | AD10: =IF(COUNTIF(Returns!$A$2:$A$1635,Orders!AC10)>0,"Returned","Not Returned") -> Not Returned
A11: 26267 | B11: High | C11: 0.04 | D11: 2.98 | E11: 1.58 | F11: 16 | G11: =IF(COUNTIF(Table1[Customer ID],Table1[[#This Row],[Customer ID]])>1,"Repeat Customer","One-Time Customer") -> Repeat Customer | H11: Sarah Ramsey | I11: Regular Air | J11: Small Business | K11: Office Supplies | L11: Rubber Bands | M11: Wrap Bag | N11: Staples Gold Paper Clips | O11: 0.39 | P11: =Table1[[#This Row],[Profit]]/Table1[[#This Row],[Sales]] -> 0.13989362 | Q11: United States | R11: East | S11: New York | T11: Syracuse | U11: 13210 | V11: 42047 | W11: =TEXT(Table1[[#This Row],[Order Date]],"mmmm") -> February | X11: =TEXT(Table1[[#This Row],[Order Date]],"yyyy") -> 2015 | Y11: 42050 | Z11: 2.63 | AA11: 6 | AB11: 18.8 | AC11: 86836 | AD11: =IF(COUNTIF(Returns!$A$2:$A$1635,Orders!AC11)>0,"Returned","Not Returned") -> Not Returned
A12: 26268 | B12: High | C12: 0.05 | D12: 115.99 | E12: 2.5 | F12: 16 | G12: =IF(COUNTIF(Table1[Customer ID],Table1[[#This Row],[Customer ID]])>1,"Repeat Customer","One-Time Customer") -> Repeat Customer | H12: Sarah Ramsey | I12: Regular Air | J12: Small Business | K12: Technology | L12: Telephones and Communication | M12: Small Box | N12: StarTAC 7797 | O12: 0.55 | P12: =Table1[[#This Row],[Profit]]/Table1[[#This Row],[Sales]] -> 0.69 | Q12: United States | R12: East | S12: New York | T12: Syracuse | U12: 13210 | V12: 42047 | W12: =TEXT(Table1[[#This Row],[Order Date]],"mmmm") -> February | X12: =TEXT(Table1[[#This Row],[Order Date]],"yyyy") -> 2015 | Y12: 42049 | Z12: 652.7331 | AA12: 10 | AB12: 945.99 | AC12: 86836 | AD12: =IF(COUNTIF(Returns!$A$2:$A$1635,Orders!AC12)>0,"Returned","Not Returned") -> Not Returned
A13: 23890 | B13: High | C13: 0.05 | D13: 26.48 | E13: 6.93 | F13: 18 | G13: =IF(COUNTIF(Table1[Customer ID],Table1[[#This Row],[Customer ID]])>1,"Repeat Customer","One-Time Customer") -> One-Time Customer | H13: Laurie Hanna | I13: Regular Air | J13: Small Business | K13: Furniture | L13: Office Furnishings | M13: Small Box | N13: DAX Natural Wood-Tone Poster Frame | O13: 0.49 | P13: =Table1[[#This Row],[Profit]]/Table1[[#This Row],[Sales]] -> 0.69 | Q13: United States | R13: West | S13: Montana | T13: Helena | U13: 59601 | V13: 42139 | W13: =TEXT(Table1[[#This Row],[Order Date]],"mmmm") -> May | X13: =TEXT(Table1[[#This Row],[Order Date]],"yyyy") -> 2015 | Y13: 42140 | Z13: 314.4813 | AA13: 17 | AB13: 455.77 | AC13: 90031 | AD13: =IF(COUNTIF(Returns!$A$2:$A$1635,Orders!AC13)>0,"Returned","Not Returned") -> Not Returned
... A182: 19158 | B182: Medium | C182: 0.01 | D182: 29.1 | E182: 4 | F182: 331 | G182: =IF(COUNTIF(Table1[Customer ID],Table1[[#This Row],[Customer ID]])>1,"Repeat Customer","One-Time Customer") -> One-Time Customer | H182: Bradley Pollock | I182: Express Air | J182: Home Office | K182: Technology | L182: Computer Peripherals | M182: Small Box | N182: Acco Keyboard-In-A-Box® | O182: 0.78 | P182: =Table1[[#This Row],[Profit]]/Table1[[#This Row],[Sales]] -> -0.093785961 | Q182: United States | R182: East | S182: New Hampshire | T182: Goffstown | U182: 3045 | V182: 42108 | W182: =TEXT(Table1[[#This Row],[Order Date]],"mmmm") -> April | X182: =TEXT(Table1[[#This Row],[Order Date]],"yyyy") -> 2015 | Y182: 42110 | Z182: -22.82 | AA182: 8 | AB182: 243.32 | AC182: 89726 | AD182: =IF(COUNTIF(Returns!$A$2:$A$1635,Orders!AC182)>0,"Returned","Not Returned") -> Not Returned
A183: 18261 | B183: Critical | C183: 0.06 | D183: 276.2 | E183: 24.49 | F183: 335 | G183: =IF(COUNTIF(Table1[Customer ID],Table1[[#This Row],[Customer ID]])>1,"Repeat Customer","One-Time Customer") -> Repeat Customer | H183: Curtis O'Connell | I183: Regular Air | J183: Corporate | K183: Furniture | L183: Chairs & Chairmats | M183: Large Box | N183: SAFCO Arco Folding Chair | P183: =Table1[[#This Row],[Profit]]/Table1[[#This Row],[Sales]] -> 0.69 | Q183: United States | R183: West | S183: Oregon | T183: Medford | U183: 97504 | V183: 42128 | W183: =TEXT(Table1[[#This Row],[Order Date]],"mmmm") -> May | X183: =TEXT(Table1[[#This Row],[Order Date]],"yyyy") -> 2015 | Y183: 42129 | Z183: 2639.4708 | AA183: 14 | AB183: 3825.32 | AC183: 87277 | AD183: =IF(COUNTIF(Returns!$A$2:$A$1635,Orders!AC183)>0,"Returned","Not Returned") -> Not Returned
A184: 18262 | B184: Critical | C184: 0.09 | D184: 6.28 | E184: 5.29 | F184: 335 | G184: =IF(COUNTIF(Table1[Customer ID],Table1[[#This Row],[Customer ID]])>1,"Repeat Customer","One-Time Customer") -> Repeat Customer | H184: Curtis O'Connell | I184: Regular Air | J184: Corporate | K184: Furniture | L184: Office Furnishings | M184: Small Box | N184: Eldon® 200 Class™ Desk Accessories, Burgundy | O184: 0.43 | P184: =Table1[[#This Row],[Profit]]/Table1[[#This Row],[Sales]] -> -0.60961313 | Q184: United States | R184: West | S184: Oregon | T184: Medford | U184: 97504 | V184: 42128 | W184: =TEXT(Table1[[#This Row],[Order Date]],"mmmm") -> May | X184: =TEXT(Table1[[#This Row],[Order Date]],"yyyy") -> 2015 | Y184: 42128 | Z184: -5.2 | AA184: 1 | AB184: 8.53 | AC184: 87277 | AD184: =IF(COUNTIF(Returns!$A$2:$A$1635,Orders!AC184)>0,"Returned","Not Returned") -> Not Returned
A185: 23481 | B185: Medium | C185: 0.08 | D185: 7.77 | E185: 9.23 | F185: 339 | G185: =IF(COUNTIF(Table1[Customer ID],Table1[[#This Row],[Customer ID]])>1,"Repeat Customer","One-Time Customer") -> Repeat Customer | H185: Bobby Clements | I185: Regular Air | J185: Corporate | K185: Office Supplies | L185: Appliances | M185: Small Box | N185: Hoover Commercial Soft Guard Upright Vacuum And Disposable Filtration Bags | O185: 0.58 | P185: =Table1[[#This Row],[Profit]]/Table1[[#This Row],[Sales]] -> -2.0756824 | Q185: United States | R185: East | S185: Ohio | T185: Columbus | U185: 43229 | V185: 42080 | W185: =TEXT(Table1[[#This Row],[Order Date]],"mmmm") -> March | X185: =TEXT(Table1[[#This Row],[Order Date]],"yyyy") -> 2015 | Y185: 42081 | Z185: -83.65 | AA185: 5 | AB185: 40.3 | AC185: 90583 | AD185: =IF(COUNTIF(Returns!$A$2:$A$1635,Orders!AC185)>0,"Returned","Not Returned") -> Not Returned
A186: 23482 | B186: Medium | C186: 0.07 | D186: 7.59 | E186: 4 | F186: 339 | G186: =IF(COUNTIF(Table1[Customer ID],Table1[[#This Row],[Customer ID]])>1,"Repeat Customer","One-Time Customer") -> Repeat Customer | H186: Bobby Clements | I186: Regular Air | J186: Corporate | K186: Furniture | L186: Office Furnishings | M186: Wrap Bag | N186: Master Giant Foot® Doorstop, Safety Yellow | O186: 0.42 | P186: =Table1[[#This Row],[Profit]]/Table1[[#This Row],[Sales]] -> 0.21800143 | Q186: United States | R186: East | S186: Ohio | T186: Columbus | U186: 43229 | V186: 42080 | W186: =TEXT(Table1[[#This Row],[Order Date]],"mmmm") -> March | X186: =TEXT(Table1[[#This Row],[Order Date]],"yyyy") -> 2015 | Y186: 42082 | Z186: 24.39 | AA186: 15 | AB186: 111.88 | AC186: 90583 | AD186: =IF(COUNTIF(Returns!$A$2:$A$1635,Orders!AC186)>0,"Returned","Not Returned") -> Not Returned
A187: 480 | B187: Critical | C187: 0.01 | D187: 3.26 | E187: 1.86 | F187: 342 | G187: =IF(COUNTIF(Table1[Customer ID],Table1[[#This Row],[Customer ID]])>1,"Repeat Customer","One-Time Customer") -> One-Time Customer | H187: Jacqueline Noble | I187: Regular Air | J187: Corporate | K187: Office Supplies | L187: Pens & Art Supplies | M187: Wrap Bag | N187: Avery Hi-Liter GlideStik Fluorescent Highlighter, Yellow Ink | O187: 0.41 | P187: =Table1[[#This Row],[Profit]]/Table1[[#This Row],[Sales]] -> -0.063110721 | Q187: United States | R187: South | S187: Florida | T187: Miami | U187: 33181 | V187: 42128 | W187: =TEXT(Table1[[#This Row],[Order Date]],"mmmm") -> May | X187: =TEXT(Table1[[#This Row],[Order Date]],"yyyy") -> 2015 | Y187: 42130 | Z187: -4.6683 | AA187: 20 | AB187: 73.97 | AC187: 3332 | AD187: =IF(COUNTIF(Returns!$A$2:$A$1635,Orders!AC187)>0,"Returned","Not Returned") -> Not Returned
A188: 22784 | B188: Critical | C188: 0.03 | D188: 15.23 | E188: 27.75 | F188: 343 | G188: =IF(COUNTIF(Table1[Customer ID],Table1[[#This Row],[Customer ID]])>1,"Repeat Customer","One-Time Customer") -> One-Time Customer | H188: Lynn Epstein | I188: Delivery Truck | J188: Corporate | K188: Furniture | L188: Tables | M188: Jumbo Box | N188: Anderson Hickey Conga Table Tops & Accessories | O188: 0.76 | P188: =Table1[[#This Row],[Profit]]/Table1[[#This Row],[Sales]] -> 0.10415653 | Q188: United States | R188: East | S188: Maine | T188: Bangor | U188: 4401 | V188: 42035 | W188: =TEXT(Table1[[#This Row],[Order Date]],"mmmm") -> January | X188: =TEXT(Table1[[#This Row],[Order Date]],"yyyy") -> 2015 | Y188: 42036 | Z188: 11.65095 | AA188: 7 | AB188: 111.86 | AC188: 88151 | AD188: =IF(COUNTIF(Returns!$A$2:$A$1635,Orders!AC188)>0,"Returned","Not Returned") -> Not Returned
A189: 18480 | B189: Critical | C189: 0.01 | D189: 3.26 | E189: 1.86 | F189: 344 | G189: =IF(COUNTIF(Table1[Customer ID],Table1[[#This Row],[Customer ID]])>1,"Repeat Customer","One-Time Customer") -> One-Time Customer | H189: Rosemary English | I189: Regular Air | J189: Corporate | K189: Office Supplies | L189: Pens & Art Supplies | M189: Wrap Bag | N189: Avery Hi-Liter GlideStik Fluorescent Highlighter, Yellow Ink | O189: 0.41 | P189: =Table1[[#This Row],[Profit]]/Table1[[#This Row],[Sales]] -> 0.037966468 | Q189: United States | R189: East | S189: Maine | T189: Portland | U189: 4101 | V189: 42128 | W189: =TEXT(Table1[[#This Row],[Order Date]],"mmmm") -> May | X189: =TEXT(Table1[[#This Row],[Order Date]],"yyyy") -> 2015 | Y189: 42130 | Z189: 0.702 | AA189: 5 | AB189: 18.49 | AC189: 88152 | AD189: =IF(COUNTIF(Returns!$A$2:$A$1635,Orders!AC189)>0,"Returned","Not Returned") -> Not Returned
A190: 2408 | B190: Critical | C190: 0 | D190: 8.34 | E190: 2.64 | F190: 349 | G190: =IF(COUNTIF(Table1[Customer ID],Table1[[#This Row],[Customer ID]])>1,"Repeat Customer","One-Time Customer") -> Repeat Customer | H190: Kim Weiss | I190: Express Air | J190: Home Office | K190: Office Supplies | L190: Scissors, Rulers and Trimmers | M190: Small Pack | N190: Acme® Elite Stainless Steel Scissors | O190: 0.59 | P190: =Table1[[#This Row],[Profit]]/Table1[[#This Row],[Sales]] -> 0.027537696 | Q190: United States | R190: South | S190: Florida | T190: Miami | U190: 33132 | V190: 42164 | W190: =TEXT(Table1[[#This Row],[Order Date]],"mmmm") -> June | X190: =TEXT(Table1[[#This Row],[Order Date]],"yyyy") -> 2015 | Y190: 42166 | Z190: 5.8625 | AA190: 23 | AB190: 212.89 | AC190: 17446 | AD190: =IF(COUNTIF(Returns!$A$2:$A$1635,Orders!AC190)>0,"Returned","Not Returned") -> Not Returned
A191: 1595 | B191: Medium | C191: 0.04 | D191: 99.23 | E191: 8.99 | F191: 349 | G191: =IF(COUNTIF(Table1[Customer ID],Table1[[#This Row],[Customer ID]])>1,"Repeat Customer","One-Time Customer") -> Repeat Customer | H191: Kim Weiss | I191: Regular Air | J191: Home Office | K191: Furniture | L191: Office Furnishings | M191: Small Pack | N191: GE 48" Fluorescent Tube, Cool White Energy Saver, 34 Watts, 30/Box | O191: 0.35 | P191: =Table1[[#This Row],[Profit]]/Table1[[#This Row],[Sales]] -> 0.34499887 | Q191: United States | R191: South | S191: Florida | T191: Miami | U191: 33132 | V191: 42006 | W191: =TEXT(Table1[[#This Row],[Order Date]],"mmmm") -> January | X191: =TEXT(Table1[[#This Row],[Order Date]],"yyyy") -> 2015 | Y191: 42008 | Z191: 1916.6757 | AA191: 54 | AB191: 5555.6 | AC191: 11527 | AD191: =IF(COUNTIF(Returns!$A$2:$A$1635,Orders!AC191)>0,"Returned","Not Returned") -> Not Returned
A192: 20408 | B192: Critical | C192: 0 | D192: 8.34 | E192: 2.64 | F192: 351 | G192: =IF(COUNTIF(Table1[Customer ID],Table1[[#This Row],[Customer ID]])>1,"Repeat Customer","One-Time Customer") -> Repeat Customer | H192: Juanita Coley Knox | I192: Express Air | J192: Home Office | K192: Office Supplies | L192: Scissors, Rulers and Trimmers | M192: Small Pack | N192: Acme® Elite Stainless Steel Scissors | O192: 0.59 | P192: =Table1[[#This Row],[Profit]]/Table1[[#This Row],[Sales]] -> 0.18905293 | Q192: United States | R192: East | S192: New York | T192: Watertown | U192: 13601 | V192: 42164 | W192: =TEXT(Table1[[#This Row],[Order Date]],"mmmm") -> June | X192: =TEXT(Table1[[#This Row],[Order Date]],"yyyy") -> 2015 | Y192: 42166 | Z192: 10.5 | AA192: 6 | AB192: 55.54 | AC192: 88685 | AD192: =IF(COUNTIF(Returns!$A$2:$A$1635,Orders!AC192)>0,"Returned","Not Returned") -> Not Returned
A193: 19595 | B193: Medium | C193: 0.04 | D193: 99.23 | E193: 8.99 | F193: 351 | G193: =IF(COUNTIF(Table1[Customer ID],Table1[[#This Row],[Customer ID]])>1,"Repeat Customer","One-Time Customer") -> Repeat Customer | H193: Juanita Coley Knox | I193: Regular Air | J193: Home Office | K193: Furniture | L193: Office Furnishings | M193: Small Pack | N193: GE 48" Fluorescent Tube, Cool White Energy Saver, 34 Watts, 30/Box | O193: 0.35 | P193: =Table1[[#This Row],[Profit]]/Table1[[#This Row],[Sales]] -> 0.69 | Q193: United States | R193: East | S193: New York | T193: Watertown | U193: 13601 | V193: 42006 | W193: =TEXT(Table1[[#This Row],[Order Date]],"mmmm") -> January | X193: =TEXT(Table1[[#This Row],[Order Date]],"yyyy") -> 2015 | Y193: 42008 | Z193: 993.8346 | AA193: 14 | AB193: 1440.34 | AC193: 88686 | AD193: =IF(COUNTIF(Returns!$A$2:$A$1635,Orders!AC193)>0,"Returned","Not Returned") -> Not Returned
A194: 19107 | B194: Low | C194: 0.08 | D194: 4.89 | E194: 4.93 | F194: 353 | G194: =IF(COUNTIF(Table1[Customer ID],Table1[[#This Row],[Customer ID]])>1,"Repeat Customer","One-Time Customer") -> Repeat Customer | H194: Bonnie Chambers | I194: Express Air | J194: Home Office | K194: Technology | L194: Computer Peripherals | M194: Small Pack | N194: Maxell 3.5" DS/HD IBM-Formatted Diskettes, 10/Pack | O194: 0.66 | P194: =Table1[[#This Row],[Profit]]/Table1[[#This Row],[Sales]] -> -1.9519821 | Q194: United States | R194: West | S194: Arizona | T194: Glendale | U194: 85301 | V194: 42138 | W194: =TEXT(Table1[[#This Row],[Order Date]],"mmmm") -> May | X194: =TEXT(Table1[[#This Row],[Order Date]],"yyyy") -> 2015 | Y194: 42138 | Z194: -165.45 | AA194: 17 | AB194: 84.76 | AC194: 89647 | AD194: =IF(COUNTIF(Returns!$A$2:$A$1635,Orders!AC194)>0,"Returned","Not Returned") -> Not Returned
A195: 19108 | B195: Low | C195: 0.07 | D195: 6.68 | E195: 6.92 | F195: 353 | G195: =IF(COUNTIF(Table1[Customer ID],Table1[[#This Row],[Customer ID]])>1,"Repeat Customer","One-Time Customer") -> Repeat Customer | H195: Bonnie Chambers | I195: Regular Air | J195: Home Office | K195: Office Supplies | L195: Paper | M195: Small Box | N195: Xerox 1898 | O195: 0.37 | P195: =Table1[[#This Row],[Profit]]/Table1[[#This Row],[Sales]] -> -1.3460511 | Q195: United States | R195: West | S195: Arizona | T195: Glendale | U195: 85301 | V195: 42138 | W195: =TEXT(Table1[[#This Row],[Order Date]],"mmmm") -> May | X195: =TEXT(Table1[[#This Row],[Order Date]],"yyyy") -> 2015 | Y195: 42145 | Z195: -141.12 | AA195: 16 | AB195: 104.84 | AC195: 89647 | AD195: =IF(COUNTIF(Returns!$A$2:$A$1635,Orders!AC195)>0,"Returned","Not Returned") -> Not Returned
... A272: 21958 | B272: High | C272: 0.01 | D272: 20.98 | E272: 53.03 | F272: 508 | G272: =IF(COUNTIF(Table1[Customer ID],Table1[[#This Row],[Customer ID]])>1,"Repeat Customer","One-Time Customer") -> Repeat Customer | H272: Cameron Owens | I272: Delivery Truck | J272: Corporate | K272: Office Supplies | L272: Storage & Organization | M272: Jumbo Drum | N272: Tennsco Lockers, Gray | O272: 0.78 | P272: =Table1[[#This Row],[Profit]]/Table1[[#This Row],[Sales]] -> -2.293348 | Q272: United States | R272: South | S272: Kentucky | T272: Covington | U272: 41011 | V272: 42058 | W272: =TEXT(Table1[[#This Row],[Order Date]],"mmmm") -> February | X272: =TEXT(Table1[[#This Row],[Order Date]],"yyyy") -> 2015 | Y272: 42058 | Z272: -282.0818 | AA272: 5 | AB272: 123 | AC272: 87356 | AD272: =IF(COUNTIF(Returns!$A$2:$A$1635,Orders!AC272)>0,"Returned","Not Returned") -> Not Returned
A273: 18305 | B273: Critical | C273: 0.01 | D273: 128.24 | E273: 12.65 | F273: 508 | G273: =IF(COUNTIF(Table1[Customer ID],Table1[[#This Row],[Customer ID]])>1,"Repeat Customer","One-Time Customer") -> Repeat Customer | H273: Cameron Owens | I273: Regular Air | J273: Corporate | K273: Furniture | L273: Chairs & Chairmats | M273: Medium Box | N273: SAFCO Folding Chair Trolley | P273: =Table1[[#This Row],[Profit]]/Table1[[#This Row],[Sales]] -> 0.25291546 | Q273: United States | R273: South | S273: Kentucky | T273: Covington | U273: 41011 | V273: 42112 | W273: =TEXT(Table1[[#This Row],[Order Date]],"mmmm") -> April | X273: =TEXT(Table1[[#This Row],[Order Date]],"yyyy") -> 2015 | Y273: 42115 | Z273: 140.1354 | AA273: 4 | AB273: 554.08 | AC273: 87357 | AD273: =IF(COUNTIF(Returns!$A$2:$A$1635,Orders!AC273)>0,"Returned","Not Returned") -> Not Returned
A274: 19895 | B274: Low | C274: 0.02 | D274: 48.04 | E274: 5.09 | F274: 510 | G274: =IF(COUNTIF(Table1[Customer ID],Table1[[#This Row],[Customer ID]])>1,"Repeat Customer","One-Time Customer") -> Repeat Customer | H274: Gregory Rao | I274: Regular Air | J274: Corporate | K274: Office Supplies | L274: Paper | M274: Small Box | N274: Xerox 1910 | O274: 0.37 | P274: =Table1[[#This Row],[Profit]]/Table1[[#This Row],[Sales]] -> 0.69 | Q274: United States | R274: West | S274: California | T274: Manteca | U274: 95336 | V274: 42017 | W274: =TEXT(Table1[[#This Row],[Order Date]],"mmmm") -> January | X274: =TEXT(Table1[[#This Row],[Order Date]],"yyyy") -> 2015 | Y274: 42017 | Z274: 105.2526 | AA274: 3 | AB274: 152.54 | AC274: 90058 | AD274: =IF(COUNTIF(Returns!$A$2:$A$1635,Orders!AC274)>0,"Returned","Not Returned") -> Not Returned
A275: 20007 | B275: Critical | C275: 0.03 | D275: 6.37 | E275: 5.19 | F275: 510 | G275: =IF(COUNTIF(Table1[Customer ID],Table1[[#This Row],[Customer ID]])>1,"Repeat Customer","One-Time Customer") -> Repeat Customer | H275: Gregory Rao | I275: Regular Air | J275: Corporate | K275: Office Supplies | L275: Binders and Binder Accessories | M275: Small Box | N275: C-Line Peel & Stick Add-On Filing Pockets, 8-3/4 x 5-1/8, 10/Pack | O275: 0.38 | P275: =Table1[[#This Row],[Profit]]/Table1[[#This Row],[Sales]] -> -0.32400824 | Q275: United States | R275: West | S275: California | T275: Manteca | U275: 95336 | V275: 42036 | W275: =TEXT(Table1[[#This Row],[Order Date]],"mmmm") -> February | X275: =TEXT(Table1[[#This Row],[Order Date]],"yyyy") -> 2015 | Y275: 42037 | Z275: -29.0927 | AA275: 14 | AB275: 89.79 | AC275: 90059 | AD275: =IF(COUNTIF(Returns!$A$2:$A$1635,Orders!AC275)>0,"Returned","Not Returned") -> Not Returned
A276: 20216 | B276: Low | C276: 0.07 | D276: 12.64 | E276: 4.98 | F276: 518 | G276: =IF(COUNTIF(Table1[Customer ID],Table1[[#This Row],[Customer ID]])>1,"Repeat Customer","One-Time Customer") -> One-Time Customer | H276: Mark Ritchie | I276: Regular Air | J276: Home Office | K276: Furniture | L276: Office Furnishings | M276: Small Pack | N276: Nu-Dell Executive Frame | O276: 0.48 | P276: =Table1[[#This Row],[Profit]]/Table1[[#This Row],[Sales]] -> 0.56775631 | Q276: United States | R276: Central | S276: Missouri | T276: Clayton | U276: 63105 | V276: 42160 | W276: =TEXT(Table1[[#This Row],[Order Date]],"mmmm") -> June | X276: =TEXT(Table1[[#This Row],[Order Date]],"yyyy") -> 2015 | Y276: 42167 | Z276: 113.415 | AA276: 16 | AB276: 199.76 | AC276: 90867 | AD276: =IF(COUNTIF(Returns!$A$2:$A$1635,Orders!AC276)>0,"Returned","Not Returned") -> Not Returned
A277: 23200 | B277: Medium | C277: 0.02 | D277: 150.98 | E277: 13.99 | F277: 522 | G277: =IF(COUNTIF(Table1[Customer ID],Table1[[#This Row],[Customer ID]])>1,"Repeat Customer","One-Time Customer") -> Repeat Customer | H277: Aaron Riggs | I277: Express Air | J277: Small Business | K277: Technology | L277: Office Machines | M277: Medium Box | N277: Canon MP41DH Printing Calculator | O277: 0.38 | P277: =Table1[[#This Row],[Profit]]/Table1[[#This Row],[Sales]] -> 0.054333118 | Q277: United States | R277: West | S277: Oregon | T277: Redmond | U277: 97756 | V277: 42177 | W277: =TEXT(Table1[[#This Row],[Order Date]],"mmmm") -> June | X277: =TEXT(Table1[[#This Row],[Order Date]],"yyyy") -> 2015 | Y277: 42179 | Z277: 26.1 | AA277: 3 | AB277: 480.37 | AC277: 89327 | AD277: =IF(COUNTIF(Returns!$A$2:$A$1635,Orders!AC277)>0,"Returned","Not Returned") -> Not Returned
A278: 23201 | B278: Medium | C278: 0.1 | D278: 5.43 | E278: 0.95 | F278: 522 | G278: =IF(COUNTIF(Table1[Customer ID],Table1[[#This Row],[Customer ID]])>1,"Repeat Customer","One-Time Customer") -> Repeat Customer | H278: Aaron Riggs | I278: Regular Air | J278: Small Business | K278: Office Supplies | L278: Paper | M278: Wrap Bag | N278: Wirebound Message Book, 4 per Page | O278: 0.36 | P278: =Table1[[#This Row],[Profit]]/Table1[[#This Row],[Sales]] -> -0.44791667 | Q278: United States | R278: West | S278: Oregon | T278: Redmond | U278: 97756 | V278: 42177 | W278: =TEXT(Table1[[#This Row],[Order Date]],"mmmm") -> June | X278: =TEXT(Table1[[#This Row],[Order Date]],"yyyy") -> 2015 | Y278: 42179 | Z278: -2.58 | AA278: 1 | AB278: 5.76 | AC278: 89327 | AD278: =IF(COUNTIF(Returns!$A$2:$A$1635,Orders!AC278)>0,"Returned","Not Returned") -> Not Returned
A279: 23202 | B279: Medium | C279: 0.01 | D279: 179.29 | E279: 29.21 | F279: 522 | G279: =IF(COUNTIF(Table1[Customer ID],Table1[[#This Row],[Customer ID]])>1,"Repeat Customer","One-Time Customer") -> Repeat Customer | H279: Aaron Riggs | I279: Delivery Truck | J279: Small Business | K279: Furniture | L279: Tables | M279: Jumbo Box | N279: Bevis Round Conference Table Top, X-Base | O279: 0.74 | P279: =Table1[[#This Row],[Profit]]/Table1[[#This Row],[Sales]] -> 0.89974391 | Q279: United States | R279: West | S279: Oregon | T279: Redmond | U279: 97756 | V279: 42177 | W279: =TEXT(Table1[[#This Row],[Order Date]],"mmmm") -> June | X279: =TEXT(Table1[[#This Row],[Order Date]],"yyyy") -> 2015 | Y279: 42178 | Z279: 2800.12 | AA279: 21 | AB279: 3112.13 | AC279: 89327 | AD279: =IF(COUNTIF(Returns!$A$2:$A$1635,Orders!AC279)>0,"Returned","Not Returned") -> Not Returned
A280: 21517 | B280: Not Specified | C280: 0.03 | D280: 1270.99 | E280: 19.99 | F280: 524 | G280: =IF(COUNTIF(Table1[Customer ID],Table1[[#This Row],[Customer ID]])>1,"Repeat Customer","One-Time Customer") -> Repeat Customer | H280: Gina McKnight | I280: Regular Air | J280: Consumer | K280: Office Supplies | L280: Binders and Binder Accessories | M280: Small Box | N280: Fellowes PB500 Electric Punch Plastic Comb Binding Machine with Manual Bind | O280: 0.35 | P280: =Table1[[#This Row],[Profit]]/Table1[[#This Row],[Sales]] -> 0.14042124 | Q280: United States | R280: South | S280: Tennessee | T280: Farragut | U280: 37922 | V280: 42024 | W280: =TEXT(Table1[[#This Row],[Order Date]],"mmmm") -> January | X280: =TEXT(Table1[[#This Row],[Order Date]],"yyyy") -> 2015 | Y280: 42026 | Z280: 363.552 | AA280: 2 | AB280: 2589.01 | AC280: 91127 | AD280: =IF(COUNTIF(Returns!$A$2:$A$1635,Orders!AC280)>0,"Returned","Not Returned") -> Not Returned
A281: 21518 | B281: Not Specified | C281: 0.07 | D281: 2036.48 | E281: 14.7 | F281: 524 | G281: =IF(COUNTIF(Table1[Customer ID],Table1[[#This Row],[Customer ID]])>1,"Repeat Customer","One-Time Customer") -> Repeat Customer | H281: Gina McKnight | I281: Delivery Truck | J281: Consumer | K281: Technology | L281: Office Machines | M281: Jumbo Drum | N281: Lexmark 4227 Plus Dot Matrix Printer | O281: 0.55 | P281: =Table1[[#This Row],[Profit]]/Table1[[#This Row],[Sales]] -> -0.0060910382 | Q281: United States | R281: South | S281: Tennessee | T281: Farragut | U281: 37922 | V281: 42024 | W281: =TEXT(Table1[[#This Row],[Order Date]],"mmmm") -> January | X281: =TEXT(Table1[[#This Row],[Order Date]],"yyyy") -> 2015 | Y281: 42026 | Z281: -11.536 | AA281: 1 | AB281: 1893.93 | AC281: 91127 | AD281: =IF(COUNTIF(Returns!$A$2:$A$1635,Orders!AC281)>0,"Returned","Not Returned") -> Not Returned
A282: 22176 | B282: High | C282: 0.09 | D282: 17.98 | E282: 8.51 | F282: 526 | G282: =IF(COUNTIF(Table1[Customer ID],Table1[[#This Row],[Customer ID]])>1,"Repeat Customer","One-Time Customer") -> Repeat Customer | H282: April Hu | I282: Regular Air | J282: Home Office | K282: Technology | L282: Office Machines | M282: Medium Box | N282: Canon P1-DHIII Palm Printing Calculator | O282: 0.4 | P282: =Table1[[#This Row],[Profit]]/Table1[[#This Row],[Sales]] -> -0.031317198 | Q282: United States | R282: West | S282: Arizona | T282: Mesa | U282: 85204 | V282: 42149 | W282: =TEXT(Table1[[#This Row],[Order Date]],"mmmm") -> May | X282: =TEXT(Table1[[#This Row],[Order Date]],"yyyy") -> 2015 | Y282: 42151 | Z282: -6.612 | AA282: 12 | AB282: 211.13 | AC282: 90026 | AD282: =IF(COUNTIF(Returns!$A$2:$A$1635,Orders!AC282)>0,"Returned","Not Returned") -> Not Returned
A283: 20494 | B283: Not Specified | C283: 0 | D283: 1.88 | E283: 1.49 | F283: 526 | G283: =IF(COUNTIF(Table1[Customer ID],Table1[[#This Row],[Customer ID]])>1,"Repeat Customer","One-Time Customer") -> Repeat Customer | H283: April Hu | I283: Regular Air | J283: Home Office | K283: Office Supplies | L283: Binders and Binder Accessories | M283: Small Box | N283: Staples® General Use 3-Ring Binders | O283: 0.37 | P283: =Table1[[#This Row],[Profit]]/Table1[[#This Row],[Sales]] -> -0.61282001 | Q283: United States | R283: West | S283: Arizona | T283: Mesa | U283: 85204 | V283: 42021 | W283: =TEXT(Table1[[#This Row],[Order Date]],"mmmm") -> January | X283: =TEXT(Table1[[#This Row],[Order Date]],"yyyy") -> 2015 | Y283: 42022 | Z283: -15.5595 | AA283: 13 | AB283: 25.39 | AC283: 90027 | AD283: =IF(COUNTIF(Returns!$A$2:$A$1635,Orders!AC283)>0,"Returned","Not Returned") -> Not Returned
A284: 20495 | B284: Not Specified | C284: 0.06 | D284: 5.78 | E284: 5.67 | F284: 526 | G284: =IF(COUNTIF(Table1[Customer ID],Table1[[#This Row],[Customer ID]])>1,"Repeat Customer","One-Time Customer") -> Repeat Customer | H284: April Hu | I284: Regular Air | J284: Home Office | K284: Office Supplies | L284: Paper | M284: Small Box | N284: Xerox 1978 | O284: 0.36 | P284: =Table1[[#This Row],[Profit]]/Table1[[#This Row],[Sales]] -> -1.2397158 | Q284: United States | R284: West | S284: Arizona | T284: Mesa | U284: 85204 | V284: 42021 | W284: =TEXT(Table1[[#This Row],[Order Date]],"mmmm") -> January | X284: =TEXT(Table1[[#This Row],[Order Date]],"yyyy") -> 2015 | Y284: 42022 | Z284: -108.19 | AA284: 15 | AB284: 87.27 | AC284: 90027 | AD284: =IF(COUNTIF(Returns!$A$2:$A$1635,Orders!AC284)>0,"Returned","Not Returned") -> Not Returned
A285: 26210 | B285: Low | C285: 0 | D285: 15.99 | E285: 13.18 | F285: 535 | G285: =IF(COUNTIF(Table1[Customer ID],Table1[[#This Row],[Customer ID]])>1,"Repeat Customer","One-Time Customer") -> One-Time Customer | H285: Jill Clements | I285: Regular Air | J285: Corporate | K285: Office Supplies | L285: Binders and Binder Accessories | M285: Small Box | N285: GBC Pre-Punched Binding Paper, Plastic, White, 8-1/2" x 11" | O285: 0.37 | P285: =Table1[[#This Row],[Profit]]/Table1[[#This Row],[Sales]] -> 0.11528332 | Q285: United States | R285: South | S285: Virginia | T285: Montclair | U285: 22025 | V285: 42115 | W285: =TEXT(Table1[[#This Row],[Order Date]],"mmmm") -> April | X285: =TEXT(Table1[[#This Row],[Order Date]],"yyyy") -> 2015 | Y285: 42119 | Z285: 46.488 | AA285: 23 | AB285: 403.25 | AC285: 88511 | AD285: =IF(COUNTIF(Returns!$A$2:$A$1635,Orders!AC285)>0,"Returned","Not Returned") -> Not Returned
... A484: 24763 | B484: Critical | C484: 0.06 | D484: 6.48 | E484: 8.88 | F484: 868 | G484: =IF(COUNTIF(Table1[Customer ID],Table1[[#This Row],[Customer ID]])>1,"Repeat Customer","One-Time Customer") -> Repeat Customer | H484: Sharon Ellis | I484: Regular Air | J484: Corporate | K484: Office Supplies | L484: Paper | M484: Small Box | N484: Xerox 224 | O484: 0.37 | P484: =Table1[[#This Row],[Profit]]/Table1[[#This Row],[Sales]] -> -1.8881291 | Q484: United States | R484: Central | S484: Minnesota | T484: Shoreview | U484: 55126 | V484: 42069 | W484: =TEXT(Table1[[#This Row],[Order Date]],"mmmm") -> March | X484: =TEXT(Table1[[#This Row],[Order Date]],"yyyy") -> 2015 | Y484: 42070 | Z484: -237.47 | AA484: 20 | AB484: 125.77 | AC484: 91195 | AD484: =IF(COUNTIF(Returns!$A$2:$A$1635,Orders!AC484)>0,"Returned","Not Returned") -> Not Returned
A485: 24764 | B485: Critical | C485: 0.09 | D485: 349.45 | E485: 60 | F485: 868 | G485: =IF(COUNTIF(Table1[Customer ID],Table1[[#This Row],[Customer ID]])>1,"Repeat Customer","One-Time Customer") -> Repeat Customer | H485: Sharon Ellis | I485: Delivery Truck | J485: Corporate | K485: Furniture | L485: Tables | M485: Jumbo Drum | N485: SAFCO PlanMaster Heigh-Adjustable Drafting Table Base, 43w x 30d x 30-37h, Black | P485: =Table1[[#This Row],[Profit]]/Table1[[#This Row],[Sales]] -> -0.75173923 | Q485: United States | R485: Central | S485: Minnesota | T485: Shoreview | U485: 55126 | V485: 42069 | W485: =TEXT(Table1[[#This Row],[Order Date]],"mmmm") -> March | X485: =TEXT(Table1[[#This Row],[Order Date]],"yyyy") -> 2015 | Y485: 42070 | Z485: -2946.051 | AA485: 12 | AB485: 3918.98 | AC485: 91195 | AD485: =IF(COUNTIF(Returns!$A$2:$A$1635,Orders!AC485)>0,"Returned","Not Returned") -> Not Returned
A486: 25507 | B486: Not Specified | C486: 0.03 | D486: 14.2 | E486: 5.3 | F486: 871 | G486: =IF(COUNTIF(Table1[Customer ID],Table1[[#This Row],[Customer ID]])>1,"Repeat Customer","One-Time Customer") -> Repeat Customer | H486: Sandy Ellington | I486: Regular Air | J486: Home Office | K486: Furniture | L486: Office Furnishings | M486: Wrap Bag | N486: Coloredge Poster Frame | O486: 0.46 | P486: =Table1[[#This Row],[Profit]]/Table1[[#This Row],[Sales]] -> 0.69 | Q486: United States | R486: West | S486: Nevada | T486: Reno | U486: 89502 | V486: 42078 | W486: =TEXT(Table1[[#This Row],[Order Date]],"mmmm") -> March | X486: =TEXT(Table1[[#This Row],[Order Date]],"yyyy") -> 2015 | Y486: 42080 | Z486: 21.5556 | AA486: 2 | AB486: 31.24 | AC486: 90577 | AD486: =IF(COUNTIF(Returns!$A$2:$A$1635,Orders!AC486)>0,"Returned","Not Returned") -> Not Returned
A487: 22547 | B487: Not Specified | C487: 0.01 | D487: 5.94 | E487: 9.92 | F487: 871 | G487: =IF(COUNTIF(Table1[Customer ID],Table1[[#This Row],[Customer ID]])>1,"Repeat Customer","One-Time Customer") -> Repeat Customer | H487: Sandy Ellington | I487: Regular Air | J487: Home Office | K487: Office Supplies | L487: Binders and Binder Accessories | M487: Small Box | N487: Storex Dura Pro™ Binders | O487: 0.38 | P487: =Table1[[#This Row],[Profit]]/Table1[[#This Row],[Sales]] -> -3.2006821 | Q487: United States | R487: West | S487: Nevada | T487: Reno | U487: 89502 | V487: 42144 | W487: =TEXT(Table1[[#This Row],[Order Date]],"mmmm") -> May | X487: =TEXT(Table1[[#This Row],[Order Date]],"yyyy") -> 2015 | Y487: 42147 | Z487: -239.315 | AA487: 12 | AB487: 74.77 | AC487: 90578 | AD487: =IF(COUNTIF(Returns!$A$2:$A$1635,Orders!AC487)>0,"Returned","Not Returned") -> Not Returned
A488: 22548 | B488: Not Specified | C488: 0 | D488: 6.48 | E488: 5.11 | F488: 871 | G488: =IF(COUNTIF(Table1[Customer ID],Table1[[#This Row],[Customer ID]])>1,"Repeat Customer","One-Time Customer") -> Repeat Customer | H488: Sandy Ellington | I488: Regular Air | J488: Home Office | K488: Office Supplies | L488: Paper | M488: Small Box | N488: Xerox 231 | O488: 0.37 | P488: =Table1[[#This Row],[Profit]]/Table1[[#This Row],[Sales]] -> -0.26062123 | Q488: United States | R488: West | S488: Nevada | T488: Reno | U488: 89502 | V488: 42144 | W488: =TEXT(Table1[[#This Row],[Order Date]],"mmmm") -> May | X488: =TEXT(Table1[[#This Row],[Order Date]],"yyyy") -> 2015 | Y488: 42146 | Z488: -33.31 | AA488: 18 | AB488: 127.81 | AC488: 90578 | AD488: =IF(COUNTIF(Returns!$A$2:$A$1635,Orders!AC488)>0,"Returned","Not Returned") -> Not Returned
A489: 19262 | B489: High | C489: 0.04 | D489: 4.37 | E489: 5.15 | F489: 875 | G489: =IF(COUNTIF(Table1[Customer ID],Table1[[#This Row],[Customer ID]])>1,"Repeat Customer","One-Time Customer") -> Repeat Customer | H489: Erika Fink | I489: Regular Air | J489: Small Business | K489: Office Supplies | L489: Appliances | M489: Small Box | N489: Eureka Sanitaire ® Multi-Pro Heavy-Duty Upright, Disposable Bags | O489: 0.59 | P489: =Table1[[#This Row],[Profit]]/Table1[[#This Row],[Sales]] -> -0.94769818 | Q489: United States | R489: West | S489: Utah | T489: Salt Lake City | U489: 84106 | V489: 42056 | W489: =TEXT(Table1[[#This Row],[Order Date]],"mmmm") -> February | X489: =TEXT(Table1[[#This Row],[Order Date]],"yyyy") -> 2015 | Y489: 42057 | Z489: -74.4796 | AA489: 18 | AB489: 78.59 | AC489: 89059 | AD489: =IF(COUNTIF(Returns!$A$2:$A$1635,Orders!AC489)>0,"Returned","Not Returned") -> Not Returned
A490: 19263 | B490: High | C490: 0.09 | D490: 155.99 | E490: 8.99 | F490: 875 | G490: =IF(COUNTIF(Table1[Customer ID],Table1[[#This Row],[Customer ID]])>1,"Repeat Customer","One-Time Customer") -> Repeat Customer | H490: Erika Fink | I490: Regular Air | J490: Small Business | K490: Technology | L490: Telephones and Communication | M490: Small Box | N490: CF 688 | O490: 0.58 | P490: =Table1[[#This Row],[Profit]]/Table1[[#This Row],[Sales]] -> -0.4671412 | Q490: United States | R490: West | S490: Utah | T490: Salt Lake City | U490: 84106 | V490: 42056 | W490: =TEXT(Table1[[#This Row],[Order Date]],"mmmm") -> February | X490: =TEXT(Table1[[#This Row],[Order Date]],"yyyy") -> 2015 | Y490: 42058 | Z490: -232.22056 | AA490: 4 | AB490: 497.11 | AC490: 89059 | AD490: =IF(COUNTIF(Returns!$A$2:$A$1635,Orders!AC490)>0,"Returned","Not Returned") -> Not Returned
A491: 18054 | B491: Critical | C491: 0.07 | D491: 5.68 | E491: 1.39 | F491: 880 | G491: =IF(COUNTIF(Table1[Customer ID],Table1[[#This Row],[Customer ID]])>1,"Repeat Customer","One-Time Customer") -> Repeat Customer | H491: Ellen Beck | I491: Regular Air | J491: Small Business | K491: Office Supplies | L491: Envelopes | M491: Small Box | N491: Staples Standard Envelopes | O491: 0.38 | P491: =Table1[[#This Row],[Profit]]/Table1[[#This Row],[Sales]] -> 0.69 | Q491: United States | R491: West | S491: Arizona | T491: Scottsdale | U491: 85254 | V491: 42088 | W491: =TEXT(Table1[[#This Row],[Order Date]],"mmmm") -> March | X491: =TEXT(Table1[[#This Row],[Order Date]],"yyyy") -> 2015 | Y491: 42090 | Z491: 18.6438 | AA491: 5 | AB491: 27.02 | AC491: 86153 | AD491: =IF(COUNTIF(Returns!$A$2:$A$1635,Orders!AC491)>0,"Returned","Not Returned") -> Not Returned
A492: 18055 | B492: Critical | C492: 0.06 | D492: 22.84 | E492: 11.54 | F492: 880 | G492: =IF(COUNTIF(Table1[Customer ID],Table1[[#This Row],[Customer ID]])>1,"Repeat Customer","One-Time Customer") -> Repeat Customer | H492: Ellen Beck | I492: Regular Air | J492: Small Business | K492: Office Supplies | L492: Paper | M492: Small Box | N492: Xerox 1964 | O492: 0.39 | P492: =Table1[[#This Row],[Profit]]/Table1[[#This Row],[Sales]] -> -1.1290206 | Q492: United States | R492: West | S492: Arizona | T492: Scottsdale | U492: 85254 | V492: 42088 | W492: =TEXT(Table1[[#This Row],[Order Date]],"mmmm") -> March | X492: =TEXT(Table1[[#This Row],[Order Date]],"yyyy") -> 2015 | Y492: 42090 | Z492: -31.24 | AA492: 1 | AB492: 27.67 | AC492: 86153 | AD492: =IF(COUNTIF(Returns!$A$2:$A$1635,Orders!AC492)>0,"Returned","Not Returned") -> Not Returned
A493: 19401 | B493: Critical | C493: 0.06 | D493: 25.98 | E493: 14.36 | F493: 885 | G493: =IF(COUNTIF(Table1[Customer ID],Table1[[#This Row],[Customer ID]])>1,"Repeat Customer","One-Time Customer") -> One-Time Customer | H493: Malcolm Robertson | I493: Delivery Truck | J493: Corporate | K493: Furniture | L493: Chairs & Chairmats | M493: Jumbo Drum | N493: Global Stack Chair without Arms, Black | O493: 0.6 | P493: =Table1[[#This Row],[Profit]]/Table1[[#This Row],[Sales]] -> 0.0540733 | Q493: United States | R493: Central | S493: Texas | T493: Amarillo | U493: 79109 | V493: 42148 | W493: =TEXT(Table1[[#This Row],[Order Date]],"mmmm") -> May | X493: =TEXT(Table1[[#This Row],[Order Date]],"yyyy") -> 2015 | Y493: 42149 | Z493: 55.888 | AA493: 41 | AB493: 1033.56 | AC493: 89537 | AD493: =IF(COUNTIF(Returns!$A$2:$A$1635,Orders!AC493)>0,"Returned","Not Returned") -> Not Returned
A494: 26011 | B494: Critical | C494: 0.08 | D494: 1.81 | E494: 0.75 | F494: 890 | G494: =IF(COUNTIF(Table1[Customer ID],Table1[[#This Row],[Customer ID]])>1,"Repeat Customer","One-Time Customer") -> Repeat Customer | H494: Billie Fowler | I494: Regular Air | J494: Consumer | K494: Furniture | L494: Chairs & Chairmats | M494: Jumbo Drum | N494: Metal Folding Chairs, Beige, 4/Carton | O494: 0.58 | P494: =Table1[[#This Row],[Profit]]/Table1[[#This Row],[Sales]] -> 0.066219329 | Q494: United States | R494: Central | S494: Texas | T494: Bedford | U494: 76021 | V494: 42009 | W494: =TEXT(Table1[[#This Row],[Order Date]],"mmmm") -> January | X494: =TEXT(Table1[[#This Row],[Order Date]],"yyyy") -> 2015 | Y494: 42010 | Z494: 1.3224 | AA494: 11 | AB494: 19.97 | AC494: 89536 | AD494: =IF(COUNTIF(Returns!$A$2:$A$1635,Orders!AC494)>0,"Returned","Not Returned") -> Not Returned
A495: 26015 | B495: Critical | C495: 0.04 | D495: 125.99 | E495: 5.26 | F495: 890 | G495: =IF(COUNTIF(Table1[Customer ID],Table1[[#This Row],[Customer ID]])>1,"Repeat Customer","One-Time Customer") -> Repeat Customer | H495: Billie Fowler | I495: Regular Air | J495: Consumer | K495: Technology | L495: Telephones and Communication | M495: Small Box | N495: 232 | O495: 0.55 | P495: =Table1[[#This Row],[Profit]]/Table1[[#This Row],[Sales]] -> 0.69 | Q495: United States | R495: Central | S495: Texas | T495: Bedford | U495: 76021 | V495: 42009 | W495: =TEXT(Table1[[#This Row],[Order Date]],"mmmm") -> January | X495: =TEXT(Table1[[#This Row],[Order Date]],"yyyy") -> 2015 | Y495: 42009 | Z495: 455.4207 | AA495: 6 | AB495: 660.03 | AC495: 89536 | AD495: =IF(COUNTIF(Returns!$A$2:$A$1635,Orders!AC495)>0,"Returned","Not Returned") -> Not Returned
A496: 2045 | B496: Critical | C496: 0.01 | D496: 8.34 | E496: 0.96 | F496: 894 | G496: =IF(COUNTIF(Table1[Customer ID],Table1[[#This Row],[Customer ID]])>1,"Repeat Customer","One-Time Customer") -> Repeat Customer | H496: Gail Rankin Cole | I496: Regular Air | J496: Corporate | K496: Furniture | L496: Office Furnishings | M496: Wrap Bag | N496: Document Clip Frames | O496: 0.43 | P496: =Table1[[#This Row],[Profit]]/Table1[[#This Row],[Sales]] -> 0.14730816 | Q496: United States | R496: East | S496: District of Columbia | T496: Washington | U496: 20024 | V496: 42014 | W496: =TEXT(Table1[[#This Row],[Order Date]],"mmmm") -> January | X496: =TEXT(Table1[[#This Row],[Order Date]],"yyyy") -> 2015 | Y496: 42016 | Z496: 29.332 | AA496: 24 | AB496: 199.12 | AC496: 14596 | AD496: =IF(COUNTIF(Returns!$A$2:$A$1635,Orders!AC496)>0,"Returned","Not Returned") -> Not Returned
A497: 2046 | B497: Critical | C497: 0.06 | D497: 3.28 | E497: 3.97 | F497: 894 | G497: =IF(COUNTIF(Table1[Customer ID],Table1[[#This Row],[Customer ID]])>1,"Repeat Customer","One-Time Customer") -> Repeat Customer | H497: Gail Rankin Cole | I497: Regular Air | J497: Corporate | K497: Office Supplies | L497: Pens & Art Supplies | M497: Wrap Bag | N497: Newell 337 | O497: 0.56 | P497: =Table1[[#This Row],[Profit]]/Table1[[#This Row],[Sales]] -> -1.3620526 | Q497: United States | R497: East | S497: District of Columbia | T497: Washington | U497: 20024 | V497: 42014 | W497: =TEXT(Table1[[#This Row],[Order Date]],"mmmm") -> January | X497: =TEXT(Table1[[#This Row],[Order Date]],"yyyy") -> 2015 | Y497: 42015 | Z497: -86 | AA497: 19 | AB497: 63.14 | AC497: 14596 | AD497: =IF(COUNTIF(Returns!$A$2:$A$1635,Orders!AC497)>0,"Returned","Not Returned") -> Not Returned
... A661: 19184 | B661: High | C661: 0.09 | D661: 40.98 | E661: 6.5 | F661: 1178 | G661: =IF(COUNTIF(Table1[Customer ID],Table1[[#This Row],[Customer ID]])>1,"Repeat Customer","One-Time Customer") -> Repeat Customer | H661: Sandy Hunt | I661: Express Air | J661: Consumer | K661: Technology | L661: Computer Peripherals | M661: Small Box | N661: Targus USB Numeric Keypad | O661: 0.74 | P661: =Table1[[#This Row],[Profit]]/Table1[[#This Row],[Sales]] -> 0.021261907 | Q661: United States | R661: South | S661: Florida | T661: Altamonte Springs | U661: 32701 | V661: 42103 | W661: =TEXT(Table1[[#This Row],[Order Date]],"mmmm") -> April | X661: =TEXT(Table1[[#This Row],[Order Date]],"yyyy") -> 2015 | Y661: 42105 | Z661: 5.6916 | AA661: 7 | AB661: 267.69 | AC661: 89787 | AD661: =IF(COUNTIF(Returns!$A$2:$A$1635,Orders!AC661)>0,"Returned","Not Returned") -> Not Returned
A662: 19185 | B662: High | C662: 0.09 | D662: 349.45 | E662: 60 | F662: 1178 | G662: =IF(COUNTIF(Table1[Customer ID],Table1[[#This Row],[Customer ID]])>1,"Repeat Customer","One-Time Customer") -> Repeat Customer | H662: Sandy Hunt | I662: Delivery Truck | J662: Consumer | K662: Furniture | L662: Tables | M662: Jumbo Drum | N662: SAFCO PlanMaster Heigh-Adjustable Drafting Table Base, 43w x 30d x 30-37h, Black | P662: =Table1[[#This Row],[Profit]]/Table1[[#This Row],[Sales]] -> -0.15997764 | Q662: United States | R662: South | S662: Florida | T662: Altamonte Springs | U662: 32701 | V662: 42103 | W662: =TEXT(Table1[[#This Row],[Order Date]],"mmmm") -> April | X662: =TEXT(Table1[[#This Row],[Order Date]],"yyyy") -> 2015 | Y662: 42104 | Z662: -369.11 | AA662: 7 | AB662: 2307.26 | AC662: 89787 | AD662: =IF(COUNTIF(Returns!$A$2:$A$1635,Orders!AC662)>0,"Returned","Not Returned") -> Not Returned
A663: 19484 | B663: High | C663: 0.07 | D663: 2.61 | E663: 0.5 | F663: 1182 | G663: =IF(COUNTIF(Table1[Customer ID],Table1[[#This Row],[Customer ID]])>1,"Repeat Customer","One-Time Customer") -> One-Time Customer | H663: Jesse Williamson | I663: Regular Air | J663: Home Office | K663: Office Supplies | L663: Labels | M663: Small Box | N663: Avery 494 | O663: 0.39 | P663: =Table1[[#This Row],[Profit]]/Table1[[#This Row],[Sales]] -> 0.69 | Q663: United States | R663: West | S663: Utah | T663: Spanish Fork | U663: 84660 | V663: 42147 | W663: =TEXT(Table1[[#This Row],[Order Date]],"mmmm") -> May | X663: =TEXT(Table1[[#This Row],[Order Date]],"yyyy") -> 2015 | Y663: 42147 | Z663: 27.0135 | AA663: 15 | AB663: 39.15 | AC663: 86913 | AD663: =IF(COUNTIF(Returns!$A$2:$A$1635,Orders!AC663)>0,"Returned","Not Returned") -> Not Returned
A664: 21522 | B664: Not Specified | C664: 0.04 | D664: 35.99 | E664: 3.3 | F664: 1183 | G664: =IF(COUNTIF(Table1[Customer ID],Table1[[#This Row],[Customer ID]])>1,"Repeat Customer","One-Time Customer") -> One-Time Customer | H664: Becky O'Brien | I664: Regular Air | J664: Home Office | K664: Technology | L664: Telephones and Communication | M664: Small Pack | N664: Accessory9 | O664: 0.39 | P664: =Table1[[#This Row],[Profit]]/Table1[[#This Row],[Sales]] -> 0.69 | Q664: United States | R664: West | S664: Utah | T664: Springville | U664: 84663 | V664: 42184 | W664: =TEXT(Table1[[#This Row],[Order Date]],"mmmm") -> June | X664: =TEXT(Table1[[#This Row],[Order Date]],"yyyy") -> 2015 | Y664: 42184 | Z664: 184.1955 | AA664: 9 | AB664: 266.95 | AC664: 86914 | AD664: =IF(COUNTIF(Returns!$A$2:$A$1635,Orders!AC664)>0,"Returned","Not Returned") -> Not Returned
A665: 22190 | B665: Medium | C665: 0 | D665: 6783.02 | E665: 24.49 | F665: 1185 | G665: =IF(COUNTIF(Table1[Customer ID],Table1[[#This Row],[Customer ID]])>1,"Repeat Customer","One-Time Customer") -> Repeat Customer | H665: Lee Xu | I665: Regular Air | J665: Consumer | K665: Technology | L665: Office Machines | M665: Large Box | N665: Polycom ViewStation™ ISDN Videoconferencing Unit | O665: 0.39 | P665: =Table1[[#This Row],[Profit]]/Table1[[#This Row],[Sales]] -> 0.00019997519 | Q665: United States | R665: South | S665: Alabama | T665: Madison | U665: 35756 | V665: 42084 | W665: =TEXT(Table1[[#This Row],[Order Date]],"mmmm") -> March | X665: =TEXT(Table1[[#This Row],[Order Date]],"yyyy") -> 2015 | Y665: 42085 | Z665: 4.11 | AA665: 3 | AB665: 20552.55 | AC665: 85938 | AD665: =IF(COUNTIF(Returns!$A$2:$A$1635,Orders!AC665)>0,"Returned","Not Returned") -> Not Returned
A666: 20764 | B666: Not Specified | C666: 0.08 | D666: 11.7 | E666: 6.96 | F666: 1185 | G666: =IF(COUNTIF(Table1[Customer ID],Table1[[#This Row],[Customer ID]])>1,"Repeat Customer","One-Time Customer") -> Repeat Customer | H666: Lee Xu | I666: Regular Air | J666: Consumer | K666: Office Supplies | L666: Appliances | M666: Medium Box | N666: Harmony HEPA Quiet Air Purifiers | O666: 0.5 | P666: =Table1[[#This Row],[Profit]]/Table1[[#This Row],[Sales]] -> 0.32535308 | Q666: United States | R666: South | S666: Alabama | T666: Madison | U666: 35756 | V666: 42104 | W666: =TEXT(Table1[[#This Row],[Order Date]],"mmmm") -> April | X666: =TEXT(Table1[[#This Row],[Order Date]],"yyyy") -> 2015 | Y666: 42107 | Z666: 28.566 | AA666: 8 | AB666: 87.8 | AC666: 85940 | AD666: =IF(COUNTIF(Returns!$A$2:$A$1635,Orders!AC666)>0,"Returned","Not Returned") -> Not Returned
A667: 24358 | B667: Critical | C667: 0.07 | D667: 400.97 | E667: 48.26 | F667: 1186 | G667: =IF(COUNTIF(Table1[Customer ID],Table1[[#This Row],[Customer ID]])>1,"Repeat Customer","One-Time Customer") -> One-Time Customer | H667: Glenda Herbert | I667: Delivery Truck | J667: Consumer | K667: Technology | L667: Office Machines | M667: Jumbo Box | N667: Hewlett-Packard Deskjet 1220Cse Color Inkjet Printer | O667: 0.36 | P667: =Table1[[#This Row],[Profit]]/Table1[[#This Row],[Sales]] -> 0.69 | Q667: United States | R667: West | S667: California | T667: Huntington Beach | U667: 92646 | V667: 42103 | W667: =TEXT(Table1[[#This Row],[Order Date]],"mmmm") -> April | X667: =TEXT(Table1[[#This Row],[Order Date]],"yyyy") -> 2015 | Y667: 42104 | Z667: 2581.5591 | AA667: 10 | AB667: 3741.39 | AC667: 85939 | AD667: =IF(COUNTIF(Returns!$A$2:$A$1635,Orders!AC667)>0,"Returned","Not Returned") -> Not Returned
A668: 18829 | B668: Low | C668: 0.06 | D668: 10.89 | E668: 4.5 | F668: 1189 | G668: =IF(COUNTIF(Table1[Customer ID],Table1[[#This Row],[Customer ID]])>1,"Repeat Customer","One-Time Customer") -> Repeat Customer | H668: Dwight Stephenson | I668: Regular Air | J668: Consumer | K668: Office Supplies | L668: Appliances | M668: Small Box | N668: Belkin 6 Outlet Metallic Surge Strip | O668: 0.59 | P668: =Table1[[#This Row],[Profit]]/Table1[[#This Row],[Sales]] -> -0.16817573 | Q668: United States | R668: West | S668: California | T668: Huntington Beach | U668: 92646 | V668: 42172 | W668: =TEXT(Table1[[#This Row],[Order Date]],"mmmm") -> June | X668: =TEXT(Table1[[#This Row],[Order Date]],"yyyy") -> 2015 | Y668: 42177 | Z668: -25.112 | AA668: 14 | AB668: 149.32 | AC668: 87584 | AD668: =IF(COUNTIF(Returns!$A$2:$A$1635,Orders!AC668)>0,"Returned","Not Returned") -> Not Returned
A669: 18830 | B669: Low | C669: 0.03 | D669: 10.64 | E669: 5.16 | F669: 1189 | G669: =IF(COUNTIF(Table1[Customer ID],Table1[[#This Row],[Customer ID]])>1,"Repeat Customer","One-Time Customer") -> Repeat Customer | H669: Dwight Stephenson | I669: Regular Air | J669: Consumer | K669: Furniture | L669: Office Furnishings | M669: Small Box | N669: Eldon Expressions Punched Metal & Wood Desk Accessories, Pewter & Cherry | O669: 0.57 | P669: =Table1[[#This Row],[Profit]]/Table1[[#This Row],[Sales]] -> 0.098163946 | Q669: United States | R669: West | S669: California | T669: Huntington Beach | U669: 92646 | V669: 42172 | W669: =TEXT(Table1[[#This Row],[Order Date]],"mmmm") -> June | X669: =TEXT(Table1[[#This Row],[Order Date]],"yyyy") -> 2015 | Y669: 42177 | Z669: 17.376 | AA669: 16 | AB669: 177.01 | AC669: 87584 | AD669: =IF(COUNTIF(Returns!$A$2:$A$1635,Orders!AC669)>0,"Returned","Not Returned") -> Not Returned
A670: 18831 | B670: Low | C670: 0.03 | D670: 7.96 | E670: 4.95 | F670: 1189 | G670: =IF(COUNTIF(Table1[Customer ID],Table1[[#This Row],[Customer ID]])>1,"Repeat Customer","One-Time Customer") -> Repeat Customer | H670: Dwight Stephenson | I670: Regular Air | J670: Consumer | K670: Furniture | L670: Office Furnishings | M670: Small Box | N670: Staples Plastic Wall Frames | O670: 0.41 | P670: =Table1[[#This Row],[Profit]]/Table1[[#This Row],[Sales]] -> 0.69 | Q670: United States | R670: West | S670: California | T670: Huntington Beach | U670: 92646 | V670: 42172 | W670: =TEXT(Table1[[#This Row],[Order Date]],"mmmm") -> June | X670: =TEXT(Table1[[#This Row],[Order Date]],"yyyy") -> 2015 | Y670: 42174 | Z670: 24.2604 | AA670: 4 | AB670: 35.16 | AC670: 87584 | AD670: =IF(COUNTIF(Returns!$A$2:$A$1635,Orders!AC670)>0,"Returned","Not Returned") -> Not Returned
A671: 19553 | B671: Low | C671: 0.03 | D671: 28.53 | E671: 1.49 | F671: 1191 | G671: =IF(COUNTIF(Table1[Customer ID],Table1[[#This Row],[Customer ID]])>1,"Repeat Customer","One-Time Customer") -> One-Time Customer | H671: John Morse | I671: Regular Air | J671: Small Business | K671: Office Supplies | L671: Binders and Binder Accessories | M671: Small Box | N671: Lock-Up Easel 'Spel-Binder' | O671: 0.38 | P671: =Table1[[#This Row],[Profit]]/Table1[[#This Row],[Sales]] -> 0.66907362 | Q671: United States | R671: East | S671: Connecticut | T671: New Britain | U671: 6050 | V671: 42183 | W671: =TEXT(Table1[[#This Row],[Order Date]],"mmmm") -> June | X671: =TEXT(Table1[[#This Row],[Order Date]],"yyyy") -> 2015 | Y671: 42186 | Z671: 59.4405 | AA671: 3 | AB671: 88.84 | AC671: 87587 | AD671: =IF(COUNTIF(Returns!$A$2:$A$1635,Orders!AC671)>0,"Returned","Not Returned") -> Not Returned
A672: 830 | B672: Low | C672: 0.03 | D672: 10.64 | E672: 5.16 | F672: 1193 | G672: =IF(COUNTIF(Table1[Customer ID],Table1[[#This Row],[Customer ID]])>1,"Repeat Customer","One-Time Customer") -> Repeat Customer | H672: Louis Parrish | I672: Regular Air | J672: Consumer | K672: Furniture | L672: Office Furnishings | M672: Small Box | N672: Eldon Expressions Punched Metal & Wood Desk Accessories, Pewter & Cherry | O672: 0.57 | P672: =Table1[[#This Row],[Profit]]/Table1[[#This Row],[Sales]] -> 0.020775941 | Q672: United States | R672: East | S672: District of Columbia | T672: Washington | U672: 20016 | V672: 42172 | W672: =TEXT(Table1[[#This Row],[Order Date]],"mmmm") -> June | X672: =TEXT(Table1[[#This Row],[Order Date]],"yyyy") -> 2015 | Y672: 42177 | Z672: 14.48 | AA672: 63 | AB672: 696.96 | AC672: 5984 | AD672: =IF(COUNTIF(Returns!$A$2:$A$1635,Orders!AC672)>0,"Returned","Not Returned") -> Not Returned
A673: 831 | B673: Low | C673: 0.03 | D673: 7.96 | E673: 4.95 | F673: 1193 | G673: =IF(COUNTIF(Table1[Customer ID],Table1[[#This Row],[Customer ID]])>1,"Repeat Customer","One-Time Customer") -> Repeat Customer | H673: Louis Parrish | I673: Regular Air | J673: Consumer | K673: Furniture | L673: Office Furnishings | M673: Small Box | N673: Staples Plastic Wall Frames | O673: 0.41 | P673: =Table1[[#This Row],[Profit]]/Table1[[#This Row],[Sales]] -> 0.14891908 | Q673: United States | R673: East | S673: District of Columbia | T673: Washington | U673: 20016 | V673: 42172 | W673: =TEXT(Table1[[#This Row],[Order Date]],"mmmm") -> June | X673: =TEXT(Table1[[#This Row],[Order Date]],"yyyy") -> 2015 | Y673: 42174 | Z673: 22.25 | AA673: 17 | AB673: 149.41 | AC673: 5984 | AD673: =IF(COUNTIF(Returns!$A$2:$A$1635,Orders!AC673)>0,"Returned","Not Returned") -> Not Returned
A674: 4131 | B674: High | C674: 0.05 | D674: 52.4 | E674: 16.11 | F674: 1193 | G674: =IF(COUNTIF(Table1[Customer ID],Table1[[#This Row],[Customer ID]])>1,"Repeat Customer","One-Time Customer") -> Repeat Customer | H674: Louis Parrish | I674: Regular Air | J674: Consumer | K674: Office Supplies | L674: Binders and Binder Accessories | M674: Small Box | N674: Ibico Laser Imprintable Binding System Covers | O674: 0.39 | P674: =Table1[[#This Row],[Profit]]/Table1[[#This Row],[Sales]] -> 0.13003612 | Q674: United States | R674: East | S674: District of Columbia | T674: Washington | U674: 20016 | V674: 42060 | W674: =TEXT(Table1[[#This Row],[Order Date]],"mmmm") -> February | X674: =TEXT(Table1[[#This Row],[Order Date]],"yyyy") -> 2015 | Y674: 42062 | Z674: 592.5265 | AA674: 85 | AB674: 4556.63 | AC674: 29350 | AD674: =IF(COUNTIF(Returns!$A$2:$A$1635,Orders!AC674)>0,"Returned","Not Returned") -> Not Returned
... A701: 19875 | B701: High | C701: 0.04 | D701: 205.99 | E701: 5.26 | F701: 1233 | G701: =IF(COUNTIF(Table1[Customer ID],Table1[[#This Row],[Customer ID]])>1,"Repeat Customer","One-Time Customer") -> Repeat Customer | H701: Gary Hester | I701: Regular Air | J701: Consumer | K701: Technology | L701: Telephones and Communication | M701: Small Box | N701: i470 | O701: 0.56 | P701: =Table1[[#This Row],[Profit]]/Table1[[#This Row],[Sales]] -> -0.00079912822 | Q701: United States | R701: Central | S701: Texas | T701: Flower Mound | U701: 75028 | V701: 42159 | W701: =TEXT(Table1[[#This Row],[Order Date]],"mmmm") -> June | X701: =TEXT(Table1[[#This Row],[Order Date]],"yyyy") -> 2015 | Y701: 42160 | Z701: -0.814 | AA701: 6 | AB701: 1018.61 | AC701: 89376 | AD701: =IF(COUNTIF(Returns!$A$2:$A$1635,Orders!AC701)>0,"Returned","Not Returned") -> Not Returned
A702: 20592 | B702: Medium | C702: 0.03 | D702: 128.24 | E702: 12.65 | F702: 1237 | G702: =IF(COUNTIF(Table1[Customer ID],Table1[[#This Row],[Customer ID]])>1,"Repeat Customer","One-Time Customer") -> Repeat Customer | H702: Eva Simpson | I702: Regular Air | J702: Corporate | K702: Furniture | L702: Chairs & Chairmats | M702: Medium Box | N702: SAFCO Folding Chair Trolley | P702: =Table1[[#This Row],[Profit]]/Table1[[#This Row],[Sales]] -> 0.69 | Q702: United States | R702: Central | S702: Texas | T702: Carrollton | U702: 75007 | V702: 42035 | W702: =TEXT(Table1[[#This Row],[Order Date]],"mmmm") -> January | X702: =TEXT(Table1[[#This Row],[Order Date]],"yyyy") -> 2015 | Y702: 42037 | Z702: 790.464 | AA702: 9 | AB702: 1145.6 | AC702: 86075 | AD702: =IF(COUNTIF(Returns!$A$2:$A$1635,Orders!AC702)>0,"Returned","Not Returned") -> Not Returned
A703: 18625 | B703: Not Specified | C703: 0.02 | D703: 7.38 | E703: 5.21 | F703: 1237 | G703: =IF(COUNTIF(Table1[Customer ID],Table1[[#This Row],[Customer ID]])>1,"Repeat Customer","One-Time Customer") -> Repeat Customer | H703: Eva Simpson | I703: Regular Air | J703: Corporate | K703: Furniture | L703: Office Furnishings | M703: Small Box | N703: Eldon® Expressions™ Wood Desk Accessories, Oak | O703: 0.56 | P703: =Table1[[#This Row],[Profit]]/Table1[[#This Row],[Sales]] -> 0.31566069 | Q703: United States | R703: Central | S703: Texas | T703: Carrollton | U703: 75007 | V703: 42092 | W703: =TEXT(Table1[[#This Row],[Order Date]],"mmmm") -> March | X703: =TEXT(Table1[[#This Row],[Order Date]],"yyyy") -> 2015 | Y703: 42093 | Z703: 7.74 | AA703: 3 | AB703: 24.52 | AC703: 86076 | AD703: =IF(COUNTIF(Returns!$A$2:$A$1635,Orders!AC703)>0,"Returned","Not Returned") -> Not Returned
A704: 20432 | B704: Medium | C704: 0.05 | D704: 300.98 | E704: 13.99 | F704: 1237 | G704: =IF(COUNTIF(Table1[Customer ID],Table1[[#This Row],[Customer ID]])>1,"Repeat Customer","One-Time Customer") -> Repeat Customer | H704: Eva Simpson | I704: Regular Air | J704: Corporate | K704: Technology | L704: Office Machines | M704: Medium Box | N704: Polycom VoiceStation 100 | O704: 0.39 | P704: =Table1[[#This Row],[Profit]]/Table1[[#This Row],[Sales]] -> 0.69 | Q704: United States | R704: Central | S704: Texas | T704: Carrollton | U704: 75007 | V704: 42149 | W704: =TEXT(Table1[[#This Row],[Order Date]],"mmmm") -> May | X704: =TEXT(Table1[[#This Row],[Order Date]],"yyyy") -> 2015 | Y704: 42150 | Z704: 3985.3089 | AA704: 20 | AB704: 5775.81 | AC704: 86077 | AD704: =IF(COUNTIF(Returns!$A$2:$A$1635,Orders!AC704)>0,"Returned","Not Returned") -> Not Returned
A705: 20433 | B705: Medium | C705: 0.04 | D705: 205.99 | E705: 5 | F705: 1237 | G705: =IF(COUNTIF(Table1[Customer ID],Table1[[#This Row],[Customer ID]])>1,"Repeat Customer","One-Time Customer") -> Repeat Customer | H705: Eva Simpson | I705: Express Air | J705: Corporate | K705: Technology | L705: Telephones and Communication | M705: Small Box | N705: Phone 918 | O705: 0.59 | P705: =Table1[[#This Row],[Profit]]/Table1[[#This Row],[Sales]] -> 0.0074307863 | Q705: United States | R705: Central | S705: Texas | T705: Carrollton | U705: 75007 | V705: 42149 | W705: =TEXT(Table1[[#This Row],[Order Date]],"mmmm") -> May | X705: =TEXT(Table1[[#This Row],[Order Date]],"yyyy") -> 2015 | Y705: 42150 | Z705: 13.9568 | AA705: 11 | AB705: 1878.24 | AC705: 86077 | AD705: =IF(COUNTIF(Returns!$A$2:$A$1635,Orders!AC705)>0,"Returned","Not Returned") -> Not Returned
A706: 20593 | B706: Medium | C706: 0.01 | D706: 160.98 | E706: 30 | F706: 1238 | G706: =IF(COUNTIF(Table1[Customer ID],Table1[[#This Row],[Customer ID]])>1,"Repeat Customer","One-Time Customer") -> One-Time Customer | H706: April Bowers | I706: Delivery Truck | J706: Corporate | K706: Furniture | L706: Chairs & Chairmats | M706: Jumbo Drum | N706: Office Star - Mid Back Dual function Ergonomic High Back Chair with 2-Way Adjustable Arms | O706: 0.62 | P706: =Table1[[#This Row],[Profit]]/Table1[[#This Row],[Sales]] -> 0.48253776 | Q706: United States | R706: Central | S706: Texas | T706: Cedar Hill | U706: 75104 | V706: 42035 | W706: =TEXT(Table1[[#This Row],[Order Date]],"mmmm") -> January | X706: =TEXT(Table1[[#This Row],[Order Date]],"yyyy") -> 2015 | Y706: 42037 | Z706: 788.79 | AA706: 10 | AB706: 1634.67 | AC706: 86075 | AD706: =IF(COUNTIF(Returns!$A$2:$A$1635,Orders!AC706)>0,"Returned","Not Returned") -> Not Returned
A707: 20920 | B707: Not Specified | C707: 0 | D707: 387.99 | E707: 19.99 | F707: 1241 | G707: =IF(COUNTIF(Table1[Customer ID],Table1[[#This Row],[Customer ID]])>1,"Repeat Customer","One-Time Customer") -> Repeat Customer | H707: Bradley Schroeder | I707: Regular Air | J707: Corporate | K707: Office Supplies | L707: Binders and Binder Accessories | M707: Small Box | N707: Fellowes PB300 Plastic Comb Binding Machine | O707: 0.38 | P707: =Table1[[#This Row],[Profit]]/Table1[[#This Row],[Sales]] -> -0.0075576033 | Q707: United States | R707: South | S707: Alabama | T707: Auburn | U707: 36830 | V707: 42079 | W707: =TEXT(Table1[[#This Row],[Order Date]],"mmmm") -> March | X707: =TEXT(Table1[[#This Row],[Order Date]],"yyyy") -> 2015 | Y707: 42080 | Z707: -70.14 | AA707: 23 | AB707: 9280.72 | AC707: 90880 | AD707: =IF(COUNTIF(Returns!$A$2:$A$1635,Orders!AC707)>0,"Returned","Not Returned") -> Not Returned
A708: 20233 | B708: Critical | C708: 0.06 | D708: 200.97 | E708: 15.59 | F708: 1241 | G708: =IF(COUNTIF(Table1[Customer ID],Table1[[#This Row],[Customer ID]])>1,"Repeat Customer","One-Time Customer") -> Repeat Customer | H708: Bradley Schroeder | I708: Delivery Truck | J708: Small Business | K708: Technology | L708: Office Machines | M708: Jumbo Drum | N708: Hewlett-Packard Deskjet 6122 Color Inkjet Printer | O708: 0.36 | P708: =Table1[[#This Row],[Profit]]/Table1[[#This Row],[Sales]] -> 0.39413269 | Q708: United States | R708: South | S708: Alabama | T708: Auburn | U708: 36830 | V708: 42088 | W708: =TEXT(Table1[[#This Row],[Order Date]],"mmmm") -> March | X708: =TEXT(Table1[[#This Row],[Order Date]],"yyyy") -> 2015 | Y708: 42088 | Z708: 531.618 | AA708: 7 | AB708: 1348.83 | AC708: 90881 | AD708: =IF(COUNTIF(Returns!$A$2:$A$1635,Orders!AC708)>0,"Returned","Not Returned") -> Not Returned
A709: 5117 | B709: High | C709: 0.1 | D709: 22.38 | E709: 15.1 | F709: 1246 | G709: =IF(COUNTIF(Table1[Customer ID],Table1[[#This Row],[Customer ID]])>1,"Repeat Customer","One-Time Customer") -> Repeat Customer | H709: Lois Hansen | I709: Regular Air | J709: Home Office | K709: Office Supplies | L709: Binders and Binder Accessories | M709: Small Box | N709: Avery Flip-Chart Easel Binder, Black | O709: 0.38 | P709: =Table1[[#This Row],[Profit]]/Table1[[#This Row],[Sales]] -> -0.19029612 | Q709: United States | R709: East | S709: New York | T709: New York City | U709: 10009 | V709: 42099 | W709: =TEXT(Table1[[#This Row],[Order Date]],"mmmm") -> April | X709: =TEXT(Table1[[#This Row],[Order Date]],"yyyy") -> 2015 | Y709: 42100 | Z709: -107.5135 | AA709: 26 | AB709: 564.98 | AC709: 36452 | AD709: =IF(COUNTIF(Returns!$A$2:$A$1635,Orders!AC709)>0,"Returned","Not Returned") -> Not Returned
A710: 5118 | B710: High | C710: 0.04 | D710: 6.98 | E710: 2.83 | F710: 1246 | G710: =IF(COUNTIF(Table1[Customer ID],Table1[[#This Row],[Customer ID]])>1,"Repeat Customer","One-Time Customer") -> Repeat Customer | H710: Lois Hansen | I710: Regular Air | J710: Home Office | K710: Furniture | L710: Office Furnishings | M710: Small Pack | N710: G.E. Halogen Desk Lamp Bulbs | O710: 0.37 | P710: =Table1[[#This Row],[Profit]]/Table1[[#This Row],[Sales]] -> 0.35534445 | Q710: United States | R710: East | S710: New York | T710: New York City | U710: 10009 | V710: 42099 | W710: =TEXT(Table1[[#This Row],[Order Date]],"mmmm") -> April | X710: =TEXT(Table1[[#This Row],[Order Date]],"yyyy") -> 2015 | Y710: 42101 | Z710: 46.01 | AA710: 18 | AB710: 129.48 | AC710: 36452 | AD710: =IF(COUNTIF(Returns!$A$2:$A$1635,Orders!AC710)>0,"Returned","Not Returned") -> Not Returned
A711: 6581 | B711: Low | C711: 0.03 | D711: 256.99 | E711: 11.25 | F711: 1246 | G711: =IF(COUNTIF(Table1[Customer ID],Table1[[#This Row],[Customer ID]])>1,"Repeat Customer","One-Time Customer") -> Repeat Customer | H711: Lois Hansen | I711: Regular Air | J711: Home Office | K711: Technology | L711: Computer Peripherals | M711: Small Box | N711: Hayes Optima 56K V.90 Internal Voice Modem | O711: 0.51 | P711: =Table1[[#This Row],[Profit]]/Table1[[#This Row],[Sales]] -> 0.18132293 | Q711: United States | R711: East | S711: New York | T711: New York City | U711: 10009 | V711: 42146 | W711: =TEXT(Table1[[#This Row],[Order Date]],"mmmm") -> May | X711: =TEXT(Table1[[#This Row],[Order Date]],"yyyy") -> 2015 | Y711: 42146 | Z711: 1489.8 | AA711: 32 | AB711: 8216.28 | AC711: 46853 | AD711: =IF(COUNTIF(Returns!$A$2:$A$1635,Orders!AC711)>0,"Returned","Not Returned") -> Not Returned
A712: 23117 | B712: High | C712: 0.1 | D712: 22.38 | E712: 15.1 | F712: 1247 | G712: =IF(COUNTIF(Table1[Customer ID],Table1[[#This Row],[Customer ID]])>1,"Repeat Customer","One-Time Customer") -> Repeat Customer | H712: Henry O'Connell | I712: Regular Air | J712: Home Office | K712: Office Supplies | L712: Binders and Binder Accessories | M712: Small Box | N712: Avery Flip-Chart Easel Binder, Black | O712: 0.38 | P712: =Table1[[#This Row],[Profit]]/Table1[[#This Row],[Sales]] -> -0.70681415 | Q712: United States | R712: Central | S712: Texas | T712: Leander | U712: 78641 | V712: 42099 | W712: =TEXT(Table1[[#This Row],[Order Date]],"mmmm") -> April | X712: =TEXT(Table1[[#This Row],[Order Date]],"yyyy") -> 2015 | Y712: 42100 | Z712: -107.5135 | AA712: 7 | AB712: 152.11 | AC712: 91555 | AD712: =IF(COUNTIF(Returns!$A$2:$A$1635,Orders!AC712)>0,"Returned","Not Returned") -> Not Returned
A713: 23118 | B713: High | C713: 0.04 | D713: 6.98 | E713: 2.83 | F713: 1247 | G713: =IF(COUNTIF(Table1[Customer ID],Table1[[#This Row],[Customer ID]])>1,"Repeat Customer","One-Time Customer") -> Repeat Customer | H713: Henry O'Connell | I713: Regular Air | J713: Home Office | K713: Furniture | L713: Office Furnishings | M713: Small Pack | N713: G.E. Halogen Desk Lamp Bulbs | O713: 0.37 | P713: =Table1[[#This Row],[Profit]]/Table1[[#This Row],[Sales]] -> 0.69 | Q713: United States | R713: Central | S713: Texas | T713: Leander | U713: 78641 | V713: 42099 | W713: =TEXT(Table1[[#This Row],[Order Date]],"mmmm") -> April | X713: =TEXT(Table1[[#This Row],[Order Date]],"yyyy") -> 2015 | Y713: 42101 | Z713: 24.8193 | AA713: 5 | AB713: 35.97 | AC713: 91555 | AD713: =IF(COUNTIF(Returns!$A$2:$A$1635,Orders!AC713)>0,"Returned","Not Returned") -> Not Returned
A714: 18413 | B714: High | C714: 0 | D714: 3.89 | E714: 7.01 | F714: 1250 | G714: =IF(COUNTIF(Table1[Customer ID],Table1[[#This Row],[Customer ID]])>1,"Repeat Customer","One-Time Customer") -> Repeat Customer | H714: Kara Patton | I714: Regular Air | J714: Corporate | K714: Office Supplies | L714: Binders and Binder Accessories | M714: Small Box | N714: Avery Binder Labels | O714: 0.37 | P714: =Table1[[#This Row],[Profit]]/Table1[[#This Row],[Sales]] -> -2.9795528 | Q714: United States | R714: Central | S714: Illinois | T714: Carpentersville | U714: 60110 | V714: 42103 | W714: =TEXT(Table1[[#This Row],[Order Date]],"mmmm") -> April | X714: =TEXT(Table1[[#This Row],[Order Date]],"yyyy") -> 2015 | Y714: 42103 | Z714: -255.1689 | AA714: 21 | AB714: 85.64 | AC714: 87877 | AD714: =IF(COUNTIF(Returns!$A$2:$A$1635,Orders!AC714)>0,"Returned","Not Returned") -> Not Returned
... A728: 22363 | B728: Critical | C728: 0.01 | D728: 13.99 | E728: 7.51 | F728: 1267 | G728: =IF(COUNTIF(Table1[Customer ID],Table1[[#This Row],[Customer ID]])>1,"Repeat Customer","One-Time Customer") -> Repeat Customer | H728: Rosemary Branch | I728: Regular Air | J728: Corporate | K728: Technology | L728: Office Machines | M728: Medium Box | N728: Sharp EL500L Fraction Calculator | O728: 0.39 | P728: =Table1[[#This Row],[Profit]]/Table1[[#This Row],[Sales]] -> 17.880804 | Q728: United States | R728: South | S728: Florida | T728: Boca Raton | U728: 33433 | V728: 42045 | W728: =TEXT(Table1[[#This Row],[Order Date]],"mmmm") -> February | X728: =TEXT(Table1[[#This Row],[Order Date]],"yyyy") -> 2015 | Y728: 42046 | Z728: 533.742 | AA728: 2 | AB728: 29.85 | AC728: 89514 | AD728: =IF(COUNTIF(Returns!$A$2:$A$1635,Orders!AC728)>0,"Returned","Not Returned") -> Not Returned
A729: 21848 | B729: Not Specified | C729: 0.08 | D729: 128.24 | E729: 12.65 | F729: 1267 | G729: =IF(COUNTIF(Table1[Customer ID],Table1[[#This Row],[Customer ID]])>1,"Repeat Customer","One-Time Customer") -> Repeat Customer | H729: Rosemary Branch | I729: Regular Air | J729: Corporate | K729: Furniture | L729: Chairs & Chairmats | M729: Medium Box | N729: SAFCO Folding Chair Trolley | P729: =Table1[[#This Row],[Profit]]/Table1[[#This Row],[Sales]] -> -1.0352145 | Q729: United States | R729: South | S729: Florida | T729: Boca Raton | U729: 33433 | V729: 42136 | W729: =TEXT(Table1[[#This Row],[Order Date]],"mmmm") -> May | X729: =TEXT(Table1[[#This Row],[Order Date]],"yyyy") -> 2015 | Y729: 42137 | Z729: -379.344 | AA729: 3 | AB729: 366.44 | AC729: 89515 | AD729: =IF(COUNTIF(Returns!$A$2:$A$1635,Orders!AC729)>0,"Returned","Not Returned") -> Not Returned
A730: 21849 | B730: Not Specified | C730: 0.04 | D730: 5.98 | E730: 4.38 | F730: 1267 | G730: =IF(COUNTIF(Table1[Customer ID],Table1[[#This Row],[Customer ID]])>1,"Repeat Customer","One-Time Customer") -> Repeat Customer | H730: Rosemary Branch | I730: Regular Air | J730: Corporate | K730: Technology | L730: Computer Peripherals | M730: Small Pack | N730: Imation 3.5" DS/HD IBM Formatted Diskettes, 10/Pack | O730: 0.75 | P730: =Table1[[#This Row],[Profit]]/Table1[[#This Row],[Sales]] -> -21.825147 | Q730: United States | R730: South | S730: Florida | T730: Boca Raton | U730: 33433 | V730: 42136 | W730: =TEXT(Table1[[#This Row],[Order Date]],"mmmm") -> May | X730: =TEXT(Table1[[#This Row],[Order Date]],"yyyy") -> 2015 | Y730: 42138 | Z730: -1522.304 | AA730: 11 | AB730: 69.75 | AC730: 89515 | AD730: =IF(COUNTIF(Returns!$A$2:$A$1635,Orders!AC730)>0,"Returned","Not Returned") -> Not Returned
A731: 19550 | B731: Medium | C731: 0.07 | D731: 125.99 | E731: 7.69 | F731: 1271 | G731: =IF(COUNTIF(Table1[Customer ID],Table1[[#This Row],[Customer ID]])>1,"Repeat Customer","One-Time Customer") -> Repeat Customer | H731: Joanne Church | I731: Regular Air | J731: Corporate | K731: Technology | L731: Telephones and Communication | M731: Small Box | N731: StarTAC 3000 | O731: 0.59 | P731: =Table1[[#This Row],[Profit]]/Table1[[#This Row],[Sales]] -> 0.69 | Q731: United States | R731: West | S731: California | T731: La Mesa | U731: 91941 | V731: 42103 | W731: =TEXT(Table1[[#This Row],[Order Date]],"mmmm") -> April | X731: =TEXT(Table1[[#This Row],[Order Date]],"yyyy") -> 2015 | Y731: 42104 | Z731: 588.2457 | AA731: 8 | AB731: 852.53 | AC731: 88410 | AD731: =IF(COUNTIF(Returns!$A$2:$A$1635,Orders!AC731)>0,"Returned","Not Returned") -> Not Returned
A732: 19398 | B732: Low | C732: 0.1 | D732: 34.23 | E732: 5.02 | F732: 1271 | G732: =IF(COUNTIF(Table1[Customer ID],Table1[[#This Row],[Customer ID]])>1,"Repeat Customer","One-Time Customer") -> Repeat Customer | H732: Joanne Church | I732: Regular Air | J732: Corporate | K732: Furniture | L732: Office Furnishings | M732: Small Box | N732: Hand-Finished Solid Wood Document Frame | O732: 0.55 | P732: =Table1[[#This Row],[Profit]]/Table1[[#This Row],[Sales]] -> 0.69 | Q732: United States | R732: West | S732: California | T732: La Mesa | U732: 91941 | V732: 42125 | W732: =TEXT(Table1[[#This Row],[Order Date]],"mmmm") -> May | X732: =TEXT(Table1[[#This Row],[Order Date]],"yyyy") -> 2015 | Y732: 42130 | Z732: 151.5654 | AA732: 7 | AB732: 219.66 | AC732: 88411 | AD732: =IF(COUNTIF(Returns!$A$2:$A$1635,Orders!AC732)>0,"Returned","Not Returned") -> Not Returned
A733: 20628 | B733: Critical | C733: 0.07 | D733: 40.98 | E733: 7.47 | F733: 1279 | G733: =IF(COUNTIF(Table1[Customer ID],Table1[[#This Row],[Customer ID]])>1,"Repeat Customer","One-Time Customer") -> Repeat Customer | H733: Josephine Rao | I733: Regular Air | J733: Corporate | K733: Office Supplies | L733: Binders and Binder Accessories | M733: Small Box | N733: Wilson Jones Ledger-Size, Piano-Hinge Binder, 2", Blue | O733: 0.37 | P733: =Table1[[#This Row],[Profit]]/Table1[[#This Row],[Sales]] -> 0.67034799 | Q733: United States | R733: Central | S733: Indiana | T733: Hammond | U733: 46324 | V733: 42064 | W733: =TEXT(Table1[[#This Row],[Order Date]],"mmmm") -> March | X733: =TEXT(Table1[[#This Row],[Order Date]],"yyyy") -> 2015 | Y733: 42065 | Z733: 54.9015 | AA733: 2 | AB733: 81.9 | AC733: 90114 | AD733: =IF(COUNTIF(Returns!$A$2:$A$1635,Orders!AC733)>0,"Returned","Not Returned") -> Not Returned
A734: 25005 | B734: Not Specified | C734: 0 | D734: 442.14 | E734: 14.7 | F734: 1279 | G734: =IF(COUNTIF(Table1[Customer ID],Table1[[#This Row],[Customer ID]])>1,"Repeat Customer","One-Time Customer") -> Repeat Customer | H734: Josephine Rao | I734: Delivery Truck | J734: Corporate | K734: Technology | L734: Office Machines | M734: Jumbo Drum | N734: Okidata ML390 Turbo Dot Matrix Printers | O734: 0.56 | P734: =Table1[[#This Row],[Profit]]/Table1[[#This Row],[Sales]] -> 0.21401504 | Q734: United States | R734: Central | S734: Indiana | T734: Hammond | U734: 46324 | V734: 42068 | W734: =TEXT(Table1[[#This Row],[Order Date]],"mmmm") -> March | X734: =TEXT(Table1[[#This Row],[Order Date]],"yyyy") -> 2015 | Y734: 42068 | Z734: 501.51 | AA734: 5 | AB734: 2343.34 | AC734: 90115 | AD734: =IF(COUNTIF(Returns!$A$2:$A$1635,Orders!AC734)>0,"Returned","Not Returned") -> Not Returned
A735: 2628 | B735: Critical | C735: 0.07 | D735: 40.98 | E735: 7.47 | F735: 1280 | G735: =IF(COUNTIF(Table1[Customer ID],Table1[[#This Row],[Customer ID]])>1,"Repeat Customer","One-Time Customer") -> One-Time Customer | H735: Harold Albright | I735: Regular Air | J735: Corporate | K735: Office Supplies | L735: Binders and Binder Accessories | M735: Small Box | N735: Wilson Jones Ledger-Size, Piano-Hinge Binder, 2", Blue | O735: 0.37 | P735: =Table1[[#This Row],[Profit]]/Table1[[#This Row],[Sales]] -> 0.16758188 | Q735: United States | R735: West | S735: Washington | T735: Seattle | U735: 98119 | V735: 42064 | W735: =TEXT(Table1[[#This Row],[Order Date]],"mmmm") -> March | X735: =TEXT(Table1[[#This Row],[Order Date]],"yyyy") -> 2015 | Y735: 42065 | Z735: 54.9015 | AA735: 8 | AB735: 327.61 | AC735: 19042 | AD735: =IF(COUNTIF(Returns!$A$2:$A$1635,Orders!AC735)>0,"Returned","Not Returned") -> Not Returned
A736: 22125 | B736: Low | C736: 0.1 | D736: 238.4 | E736: 24.49 | F736: 1281 | G736: =IF(COUNTIF(Table1[Customer ID],Table1[[#This Row],[Customer ID]])>1,"Repeat Customer","One-Time Customer") -> Repeat Customer | H736: Pauline Denton | I736: Regular Air | J736: Small Business | K736: Furniture | L736: Chairs & Chairmats | M736: Large Box | N736: Safco Contoured Stacking Chairs | P736: =Table1[[#This Row],[Profit]]/Table1[[#This Row],[Sales]] -> 0.49325692 | Q736: United States | R736: Central | S736: Indiana | T736: Vincennes | U736: 47591 | V736: 42028 | W736: =TEXT(Table1[[#This Row],[Order Date]],"mmmm") -> January | X736: =TEXT(Table1[[#This Row],[Order Date]],"yyyy") -> 2015 | Y736: 42030 | Z736: 875.2844 | AA736: 8 | AB736: 1774.5 | AC736: 89112 | AD736: =IF(COUNTIF(Returns!$A$2:$A$1635,Orders!AC736)>0,"Returned","Not Returned") -> Not Returned
A737: 22126 | B737: Low | C737: 0.03 | D737: 199.99 | E737: 24.49 | F737: 1281 | G737: =IF(COUNTIF(Table1[Customer ID],Table1[[#This Row],[Customer ID]])>1,"Repeat Customer","One-Time Customer") -> Repeat Customer | H737: Pauline Denton | I737: Express Air | J737: Small Business | K737: Technology | L737: Copiers and Fax | M737: Large Box | N737: Canon PC-428 Personal Copier | O737: 0.46 | P737: =Table1[[#This Row],[Profit]]/Table1[[#This Row],[Sales]] -> 0.69 | Q737: United States | R737: Central | S737: Indiana | T737: Vincennes | U737: 47591 | V737: 42028 | W737: =TEXT(Table1[[#This Row],[Order Date]],"mmmm") -> January | X737: =TEXT(Table1[[#This Row],[Order Date]],"yyyy") -> 2015 | Y737: 42030 | Z737: 727.7361 | AA737: 5 | AB737: 1054.69 | AC737: 89112 | AD737: =IF(COUNTIF(Returns!$A$2:$A$1635,Orders!AC737)>0,"Returned","Not Returned") -> Not Returned
A738: 4125 | B738: Low | C738: 0.1 | D738: 238.4 | E738: 24.49 | F738: 1282 | G738: =IF(COUNTIF(Table1[Customer ID],Table1[[#This Row],[Customer ID]])>1,"Repeat Customer","One-Time Customer") -> Repeat Customer | H738: Dana Sharpe | I738: Regular Air | J738: Small Business | K738: Furniture | L738: Chairs & Chairmats | M738: Large Box | N738: Safco Contoured Stacking Chairs | P738: =Table1[[#This Row],[Profit]]/Table1[[#This Row],[Sales]] -> 0.069228885 | Q738: United States | R738: East | S738: Pennsylvania | T738: Philadelphia | U738: 19134 | V738: 42028 | W738: =TEXT(Table1[[#This Row],[Order Date]],"mmmm") -> January | X738: =TEXT(Table1[[#This Row],[Order Date]],"yyyy") -> 2015 | Y738: 42030 | Z738: 460.676 | AA738: 30 | AB738: 6654.39 | AC738: 29319 | AD738: =IF(COUNTIF(Returns!$A$2:$A$1635,Orders!AC738)>0,"Returned","Not Returned") -> Not Returned
A739: 4126 | B739: Low | C739: 0.03 | D739: 199.99 | E739: 24.49 | F739: 1282 | G739: =IF(COUNTIF(Table1[Customer ID],Table1[[#This Row],[Customer ID]])>1,"Repeat Customer","One-Time Customer") -> Repeat Customer | H739: Dana Sharpe | I739: Express Air | J739: Small Business | K739: Technology | L739: Copiers and Fax | M739: Large Box | N739: Canon PC-428 Personal Copier | O739: 0.46 | P739: =Table1[[#This Row],[Profit]]/Table1[[#This Row],[Sales]] -> 0.088814341 | Q739: United States | R739: East | S739: Pennsylvania | T739: Philadelphia | U739: 19134 | V739: 42028 | W739: =TEXT(Table1[[#This Row],[Order Date]],"mmmm") -> January | X739: =TEXT(Table1[[#This Row],[Order Date]],"yyyy") -> 2015 | Y739: 42030 | Z739: 393.42 | AA739: 21 | AB739: 4429.69 | AC739: 29319 | AD739: =IF(COUNTIF(Returns!$A$2:$A$1635,Orders!AC739)>0,"Returned","Not Returned") -> Not Returned
A740: 19990 | B740: Not Specified | C740: 0.04 | D740: 150.98 | E740: 13.99 | F740: 1298 | G740: =IF(COUNTIF(Table1[Customer ID],Table1[[#This Row],[Customer ID]])>1,"Repeat Customer","One-Time Customer") -> Repeat Customer | H740: Herbert Beard | I740: Regular Air | J740: Home Office | K740: Technology | L740: Office Machines | M740: Medium Box | N740: Canon MP41DH Printing Calculator | O740: 0.38 | P740: =Table1[[#This Row],[Profit]]/Table1[[#This Row],[Sales]] -> 0.69 | Q740: United States | R740: Central | S740: Texas | T740: Sulphur Springs | U740: 75482 | V740: 42047 | W740: =TEXT(Table1[[#This Row],[Order Date]],"mmmm") -> February | X740: =TEXT(Table1[[#This Row],[Order Date]],"yyyy") -> 2015 | Y740: 42050 | Z740: 606.0546 | AA740: 6 | AB740: 878.34 | AC740: 90662 | AD740: =IF(COUNTIF(Returns!$A$2:$A$1635,Orders!AC740)>0,"Returned","Not Returned") -> Not Returned
A741: 19991 | B741: Not Specified | C741: 0.04 | D741: 176.19 | E741: 11.87 | F741: 1298 | G741: =IF(COUNTIF(Table1[Customer ID],Table1[[#This Row],[Customer ID]])>1,"Repeat Customer","One-Time Customer") -> Repeat Customer | H741: Herbert Beard | I741: Regular Air | J741: Home Office | K741: Office Supplies | L741: Storage & Organization | M741: Small Box | N741: Fellowes High-Stak® Drawer Files | O741: 0.62 | P741: =Table1[[#This Row],[Profit]]/Table1[[#This Row],[Sales]] -> 0.47312178 | Q741: United States | R741: Central | S741: Texas | T741: Sulphur Springs | U741: 75482 | V741: 42047 | W741: =TEXT(Table1[[#This Row],[Order Date]],"mmmm") -> February | X741: =TEXT(Table1[[#This Row],[Order Date]],"yyyy") -> 2015 | Y741: 42049 | Z741: 320.1 | AA741: 4 | AB741: 676.57 | AC741: 90662 | AD741: =IF(COUNTIF(Returns!$A$2:$A$1635,Orders!AC741)>0,"Returned","Not Returned") -> Not Returned
A742: 23120 | B742: High | C742: 0.03 | D742: 39.48 | E742: 1.99 | F742: 1303 | G742: =IF(COUNTIF(Table1[Customer ID],Table1[[#This Row],[Customer ID]])>1,"Repeat Customer","One-Time Customer") -> Repeat Customer | H742: Cindy Harvey | I742: Regular Air | J742: Consumer | K742: Technology | L742: Computer Peripherals | M742: Small Pack | N742: 80 Minute CD-R Spindle, 100/Pack - Staples | O742: 0.54 | P742: =Table1[[#This Row],[Profit]]/Table1[[#This Row],[Sales]] -> 0.69 | Q742: United States | R742: West | S742: Utah | T742: Tooele | U742: 84074 | V742: 42054 | W742: =TEXT(Table1[[#This Row],[Order Date]],"mmmm") -> February | X742: =TEXT(Table1[[#This Row],[Order Date]],"yyyy") -> 2015 | Y742: 42056 | Z742: 317.0895 | AA742: 12 | AB742: 459.55 | AC742: 87003 | AD742: =IF(COUNTIF(Returns!$A$2:$A$1635,Orders!AC742)>0,"Returned","Not Returned") -> Not Returned
A743: 20652 | B743: Low | C743: 0.01 | D743: 65.99 | E743: 5.31 | F743: 1303 | G743: =IF(COUNTIF(Table1[Customer ID],Table1[[#This Row],[Customer ID]])>1,"Repeat Customer","One-Time Customer") -> Repeat Customer | H743: Cindy Harvey | I743: Regular Air | J743: Consumer | K743: Technology | L743: Telephones and Communication | M743: Small Box | N743: 3390 | O743: 0.57 | P743: =Table1[[#This Row],[Profit]]/Table1[[#This Row],[Sales]] -> 0.46631164 | Q743: United States | R743: West | S743: Utah | T743: Tooele | U743: 84074 | V743: 42054 | W743: =TEXT(Table1[[#This Row],[Order Date]],"mmmm") -> February | X743: =TEXT(Table1[[#This Row],[Order Date]],"yyyy") -> 2015 | Y743: 42061 | Z743: 250.36272 | AA743: 9 | AB743: 536.9 | AC743: 87005 | AD743: =IF(COUNTIF(Returns!$A$2:$A$1635,Orders!AC743)>0,"Returned","Not Returned") -> Not Returned
A744: 25092 | B744: Medium | C744: 0.08 | D744: 2.88 | E744: 0.5 | F744: 1304 | G744: =IF(COUNTIF(Table1[Customer ID],Table1[[#This Row],[Customer ID]])>1,"Repeat Customer","One-Time Customer") -> One-Time Customer | H744: Sherri McIntosh | I744: Regular Air | J744: Consumer | K744: Office Supplies | L744: Labels | M744: Small Box | N744: Avery 507 | O744: 0.39 | P744: =Table1[[#This Row],[Profit]]/Table1[[#This Row],[Sales]] -> 0.69 | Q744: United States | R744: West | S744: Utah | T744: West Jordan | U744: 84084 | V744: 42117 | W744: =TEXT(Table1[[#This Row],[Order Date]],"mmmm") -> April | X744: =TEXT(Table1[[#This Row],[Order Date]],"yyyy") -> 2015 | Y744: 42118 | Z744: 6.0306 | AA744: 3 | AB744: 8.74 | AC744: 87004 | AD744: =IF(COUNTIF(Returns!$A$2:$A$1635,Orders!AC744)>0,"Returned","Not Returned") -> Not Returned
...

Sheet Returns
A1: Order ID | B1: Status
A2: 65 | B2: Returned
A3: 612 | B3: Returned
A4: 614 | B4: Returned
A5: 678 | B5: Returned
A6: 710 | B6: Returned
A7: 740 | B7: Returned
A8: 775 | B8: Returned
A9: 833 | B9: Returned
A10: 902 | B10: Returned
A11: 3300 | B11: Returned
A12: 3456 | B12: Returned
A13: 3525 | B13: Returned
... A1635: 182906 | B1635: Returned
